[
  {
    "coinCount": "1.70w",
    "face": "https://i1.hdslb.com/bfs/face/f40e1f6f2ea9c00d7ea7bce05cbf21c9320c6c05.jpg",
    "followerDiff": "4.86w",
    "isCollect": null,
    "level": "6",
    "likeCount": "13.82w",
    "maxSex": null,
    "mid": "1646036311",
    "name": "凤凰传奇",
    "newrankIndex": "951.0",
    "officialTitle": "bilibili 2021百大UP主、音乐组合凤凰传奇官方账号",
    "officialType": "0",
    "opusCount": "1",
    "playCount": "120.99w",
    "profession": null,
    "rankPosition": 111,
    "sex": "保密",
    "type": "音乐",
    "videoReviewCount": "2806"
  },
  {
    "coinCount": "3.04w",
    "face": "https://i1.hdslb.com/bfs/face/16308da75f93c0ac679d0977a4eb9e2b8a8aa312.jpg",
    "followerDiff": "1.84w",
    "isCollect": null,
    "level": "6",
    "likeCount": "5.21w",
    "maxSex": null,
    "mid": "37754047",
    "name": "咻咻满",
    "newrankIndex": "950.8",
    "officialTitle": "bilibili 2022百大UP主、知名音乐UP主",
    "officialType": "0",
    "opusCount": "1",
    "playCount": "77.98w",
    "profession": null,
    "rankPosition": 113,
    "sex": "女",
    "type": "音乐",
    "videoReviewCount": "1604"
  },
  {
    "coinCount": "7.75w",
    "face": "https://i1.hdslb.com/bfs/face/15e02d71eae286a767e156f15cf066e41a9a0ec9.jpg",
    "followerDiff": "3279",
    "isCollect": null,
    "level": "6",
    "likeCount": "8.80w",
    "maxSex": null,
    "mid": "110352985",
    "name": "GARNiDELiA",
    "newrankIndex": "949.3",
    "officialTitle": "GARNiDELiA官方账号",
    "officialType": "0",
    "opusCount": "1",
    "playCount": "57.37w",
    "profession": null,
    "rankPosition": 116,
    "sex": "保密",
    "type": "音乐",
    "videoReviewCount": "1.39w"
  },
  {
    "coinCount": "1.57w",
    "face": "https://i0.hdslb.com/bfs/face/a73660e10c210c4933f9ef496c756b5aee253917.jpg",
    "followerDiff": "1.90w",
    "isCollect": null,
    "level": "6",
    "likeCount": "15.41w",
    "maxSex": null,
    "mid": "11253297",
    "name": "多多poi丶",
    "newrankIndex": "947.0",
    "officialTitle": "bilibili 2021百大UP主、直播高能主播、配音演员、声优",
    "officialType": "0",
    "opusCount": "1",
    "playCount": "109.03w",
    "profession": null,
    "rankPosition": 125,
    "sex": "女",
    "type": "音乐",
    "videoReviewCount": "1583"
  },
  {
    "coinCount": "2.92w",
    "face": "https://i2.hdslb.com/bfs/face/0da24ae60a20f0f00855a534678864d095d0e900.jpg",
    "followerDiff": "1.64w",
    "isCollect": null,
    "level": "6",
    "likeCount": "13.13w",
    "maxSex": null,
    "mid": "3493082817366845",
    "name": "JLRS-jayfm",
    "newrankIndex": "942.3",
    "officialTitle": "bilibili 知名音乐UP主",
    "officialType": "0",
    "opusCount": "24",
    "playCount": "135.39w",
    "profession": null,
    "rankPosition": 135,
    "sex": "男",
    "type": "音乐",
    "videoReviewCount": "3447"
  },
  {
    "coinCount": "2.77w",
    "face": "https://i2.hdslb.com/bfs/face/bf1e658491855cfce7af3e9ca1eb9125eaab9dd5.jpg",
    "followerDiff": "1.12w",
    "isCollect": null,
    "level": "6",
    "likeCount": "9.01w",
    "maxSex": null,
    "mid": "631070414",
    "name": "折原露露",
    "newrankIndex": "940.4",
    "officialTitle": "bilibili 知名虚拟UP主",
    "officialType": "0",
    "opusCount": "3",
    "playCount": "68.11w",
    "profession": null,
    "rankPosition": 142,
    "sex": "保密",
    "type": "音乐",
    "videoReviewCount": "3574"
  },
  {
    "coinCount": "3.66w",
    "face": "https://i2.hdslb.com/bfs/face/1ac383d18dc8cf2900196e72d8279d12b10cb4fc.jpg",
    "followerDiff": "2.48w",
    "isCollect": null,
    "level": "6",
    "likeCount": "22.35w",
    "maxSex": null,
    "mid": "311671229",
    "name": "JasonHuangMusic",
    "newrankIndex": "935.4",
    "officialTitle": "bilibili 知名音乐UP主",
    "officialType": "0",
    "opusCount": "1",
    "playCount": "163.75w",
    "profession": null,
    "rankPosition": 159,
    "sex": "男",
    "type": "音乐",
    "videoReviewCount": "1681"
  },
  {
    "coinCount": "1.40w",
    "face": "http://i2.hdslb.com/bfs/face/f4475f7a56a13d0553f471b0ae851fc14decb4d5.jpg",
    "followerDiff": "2001",
    "isCollect": null,
    "level": "6",
    "likeCount": "23.26w",
    "maxSex": null,
    "mid": "16720403",
    "name": "pcyxjy",
    "newrankIndex": "934.3",
    "officialTitle": "bilibili 知名娱乐UP主",
    "officialType": "0",
    "opusCount": "57",
    "playCount": "465.70w",
    "profession": null,
    "rankPosition": 164,
    "sex": "女",
    "type": "音乐",
    "videoReviewCount": "2.54w"
  },
  {
    "coinCount": "1.42w",
    "face": "https://i1.hdslb.com/bfs/face/8a261de4941718ab8456fe183d7bcf7d9b3d729b.jpg",
    "followerDiff": "6.40w",
    "isCollect": null,
    "level": "3",
    "likeCount": "8.43w",
    "maxSex": null,
    "mid": "3537106035018583",
    "name": "RIIZE",
    "newrankIndex": "920.2",
    "officialTitle": "",
    "officialType": "-1",
    "opusCount": "30",
    "playCount": "108.37w",
    "profession": null,
    "rankPosition": 221,
    "sex": "保密",
    "type": "音乐",
    "videoReviewCount": "1.47w"
  },
  {
    "coinCount": "3.86w",
    "face": "https://i1.hdslb.com/bfs/face/4772a11480150949bae49d30e4ed391ef91982ec.jpg",
    "followerDiff": "7.85w",
    "isCollect": null,
    "level": "2",
    "likeCount": "33.49w",
    "maxSex": null,
    "mid": "3537123875489860",
    "name": "李彩演",
    "newrankIndex": "918.3",
    "officialTitle": "李彩演官方账号",
    "officialType": "0",
    "opusCount": "11",
    "playCount": "212.51w",
    "profession": null,
    "rankPosition": 236,
    "sex": "保密",
    "type": "音乐",
    "videoReviewCount": "2411"
  },
  {
    "coinCount": "3.80w",
    "face": "http://i1.hdslb.com/bfs/face/2e25812e0ba75174c07fe9b61e68e20c66e89499.jpg",
    "followerDiff": "2721",
    "isCollect": null,
    "level": "6",
    "likeCount": "6.12w",
    "maxSex": null,
    "mid": "3379951",
    "name": "ilem",
    "newrankIndex": "914.0",
    "officialTitle": "bilibili 2019百大UP主",
    "officialType": "0",
    "opusCount": "1",
    "playCount": "42.51w",
    "profession": null,
    "rankPosition": 248,
    "sex": "男",
    "type": "音乐",
    "videoReviewCount": "897"
  },
  {
    "coinCount": "1.71w",
    "face": "https://i0.hdslb.com/bfs/face/fcf4d035bb3eb00c576df45c8709cb53d7e69d37.jpg",
    "followerDiff": "1.54w",
    "isCollect": null,
    "level": "6",
    "likeCount": "4.12w",
    "maxSex": null,
    "mid": "1023951201",
    "name": "拉美小姐姐Waleska",
    "newrankIndex": "911.7",
    "officialTitle": "Waleska Herrera 官方账号",
    "officialType": "0",
    "opusCount": "2",
    "playCount": "89.27w",
    "profession": null,
    "rankPosition": 263,
    "sex": "保密",
    "type": "音乐",
    "videoReviewCount": "6227"
  },
  {
    "coinCount": "1.53w",
    "face": "https://i1.hdslb.com/bfs/face/c44d2511128e6dde5f70f3d5c22b2fe025ba1fd2.jpg",
    "followerDiff": "2526",
    "isCollect": null,
    "level": "6",
    "likeCount": "12.21w",
    "maxSex": null,
    "mid": "673375678",
    "name": "NCT",
    "newrankIndex": "908.9",
    "officialTitle": "男子偶像组合NCT官方账号",
    "officialType": "0",
    "opusCount": "23",
    "playCount": "137.68w",
    "profession": null,
    "rankPosition": 274,
    "sex": "保密",
    "type": "音乐",
    "videoReviewCount": "7425"
  },
  {
    "coinCount": "7.80w",
    "face": "http://i1.hdslb.com/bfs/face/5059409aff540162abde1053873566d94970bbb2.jpg",
    "followerDiff": "6570",
    "isCollect": null,
    "level": "6",
    "likeCount": "18.98w",
    "maxSex": null,
    "mid": "20804689",
    "name": "李宇春疯狂工作室",
    "newrankIndex": "907.5",
    "officialTitle": "北京黄色石头传媒有限公司",
    "officialType": "1",
    "opusCount": "1",
    "playCount": "274.45w",
    "profession": null,
    "rankPosition": 283,
    "sex": "女",
    "type": "音乐",
    "videoReviewCount": "2.53w"
  },
  {
    "coinCount": "1.72w",
    "face": "https://i2.hdslb.com/bfs/face/dac3b802761b68423a95411a19d77e0ae45fe8a2.jpg",
    "followerDiff": "2.82w",
    "isCollect": null,
    "level": "6",
    "likeCount": "23.06w",
    "maxSex": null,
    "mid": "494512664",
    "name": "三套车乐队",
    "newrankIndex": "906.6",
    "officialTitle": "",
    "officialType": "-1",
    "opusCount": "2",
    "playCount": "217.06w",
    "profession": null,
    "rankPosition": 289,
    "sex": "男",
    "type": "音乐",
    "videoReviewCount": "549"
  },
  {
    "coinCount": "7161",
    "face": "https://i2.hdslb.com/bfs/face/0f1d960ca6baad6c0f008cba48dfc6ba17c2738d.jpg",
    "followerDiff": "1.12w",
    "isCollect": null,
    "level": "6",
    "likeCount": "3.92w",
    "maxSex": null,
    "mid": "7295246",
    "name": "JKAI杰凯",
    "newrankIndex": "905.0",
    "officialTitle": "bilibili 知名音乐UP主",
    "officialType": "0",
    "opusCount": "4",
    "playCount": "111.94w",
    "profession": null,
    "rankPosition": 299,
    "sex": "男",
    "type": "音乐",
    "videoReviewCount": "1.30w"
  },
  {
    "coinCount": "4850",
    "face": "https://i1.hdslb.com/bfs/face/b70f30462bc1335383161fabc24556d3e924e8e5.jpg",
    "followerDiff": "4999",
    "isCollect": null,
    "level": "6",
    "likeCount": "2.87w",
    "maxSex": null,
    "mid": "65553886",
    "name": "SavageTurely",
    "newrankIndex": "904.5",
    "officialTitle": "bilibili 知名音乐UP主",
    "officialType": "0",
    "opusCount": "2",
    "playCount": "85.97w",
    "profession": null,
    "rankPosition": 302,
    "sex": "保密",
    "type": "音乐",
    "videoReviewCount": "2.73w"
  },
  {
    "coinCount": "7345",
    "face": "https://i2.hdslb.com/bfs/face/837f90e96e85b1cc79d9c0e38bba9d3e106b9489.jpg",
    "followerDiff": "2725",
    "isCollect": null,
    "level": "6",
    "likeCount": "9.94w",
    "maxSex": null,
    "mid": "226178777",
    "name": "街头社区",
    "newrankIndex": "898.7",
    "officialTitle": "bilibili 知名音乐UP主",
    "officialType": "0",
    "opusCount": "21",
    "playCount": "313.54w",
    "profession": null,
    "rankPosition": 353,
    "sex": "保密",
    "type": "音乐",
    "videoReviewCount": "3152"
  },
  {
    "coinCount": "9792",
    "face": "https://i2.hdslb.com/bfs/face/04cf6797dd026ac838847ad11c85b14f48466cf6.jpg",
    "followerDiff": "6579",
    "isCollect": null,
    "level": "6",
    "likeCount": "3.87w",
    "maxSex": null,
    "mid": "2087881184",
    "name": "XGALX_XG",
    "newrankIndex": "884.5",
    "officialTitle": "女子组合XG官方账号",
    "officialType": "0",
    "opusCount": "3",
    "playCount": "35.43w",
    "profession": null,
    "rankPosition": 464,
    "sex": "女",
    "type": "音乐",
    "videoReviewCount": "3755"
  },
  {
    "coinCount": "8578",
    "face": "https://i0.hdslb.com/bfs/face/b14b51c6112218ceeb6b16c3453d08bb5ff2a83c.jpg",
    "followerDiff": "1.17w",
    "isCollect": null,
    "level": "6",
    "likeCount": "3.66w",
    "maxSex": null,
    "mid": "698029620",
    "name": "兰音Reine",
    "newrankIndex": "879.0",
    "officialTitle": "bilibili 知名音乐UP主",
    "officialType": "0",
    "opusCount": "2",
    "playCount": "31.25w",
    "profession": null,
    "rankPosition": 509,
    "sex": "女",
    "type": "音乐",
    "videoReviewCount": "231"
  },
  {
    "coinCount": "7899",
    "face": "https://i1.hdslb.com/bfs/face/b58d774d803664e838196cd5ce4bbfa3ca7bdfa0.jpg",
    "followerDiff": "5845",
    "isCollect": null,
    "level": "6",
    "likeCount": "2.59w",
    "maxSex": null,
    "mid": "261485584",
    "name": "HOPICO",
    "newrankIndex": "878.6",
    "officialTitle": "bilibili 2022百大UP主、知名UP主",
    "officialType": "0",
    "opusCount": "1",
    "playCount": "27.68w",
    "profession": null,
    "rankPosition": 515,
    "sex": "男",
    "type": "音乐",
    "videoReviewCount": "836"
  },
  {
    "coinCount": "6344",
    "face": "https://i1.hdslb.com/bfs/face/73b4a9c72551cd57b06b29d55215b3c9897a0dca.jpg",
    "followerDiff": "7763",
    "isCollect": null,
    "level": "6",
    "likeCount": "2.29w",
    "maxSex": null,
    "mid": "313580179",
    "name": "九三的耳朵不是特别好",
    "newrankIndex": "878.4",
    "officialTitle": "bilibili 2022百大UP主、知名音乐UP主",
    "officialType": "0",
    "opusCount": "1",
    "playCount": "38.47w",
    "profession": null,
    "rankPosition": 518,
    "sex": "保密",
    "type": "音乐",
    "videoReviewCount": "433"
  },
  {
    "coinCount": "2.21w",
    "face": "https://i0.hdslb.com/bfs/face/60c67044c67178b614660a233729caeec936d68e.jpg",
    "followerDiff": "6534",
    "isCollect": null,
    "level": "6",
    "likeCount": "5.41w",
    "maxSex": null,
    "mid": "678797523",
    "name": "V在燃烧",
    "newrankIndex": "875.7",
    "officialTitle": "bilibili 知名UP主",
    "officialType": "0",
    "opusCount": "1",
    "playCount": "37.13w",
    "profession": null,
    "rankPosition": 538,
    "sex": "保密",
    "type": "音乐",
    "videoReviewCount": "313"
  },
  {
    "coinCount": "5698",
    "face": "https://i2.hdslb.com/bfs/face/b7c702eff923c8b0d5db39a91cac746e10bdb60e.jpg",
    "followerDiff": "9774",
    "isCollect": null,
    "level": "6",
    "likeCount": "4.75w",
    "maxSex": null,
    "mid": "434656505",
    "name": "二手玫瑰乐队",
    "newrankIndex": "866.7",
    "officialTitle": "二手玫瑰乐队官方账号",
    "officialType": "0",
    "opusCount": "3",
    "playCount": "78.76w",
    "profession": null,
    "rankPosition": 618,
    "sex": "男",
    "type": "音乐",
    "videoReviewCount": "851"
  },
  {
    "coinCount": "6598",
    "face": "https://i0.hdslb.com/bfs/face/18b51273dd2714f34ca504c47cbbefaeb24c96f7.jpg",
    "followerDiff": "4620",
    "isCollect": null,
    "level": "6",
    "likeCount": "2.49w",
    "maxSex": null,
    "mid": "540564177",
    "name": "Jason-老湿",
    "newrankIndex": "864.9",
    "officialTitle": "bilibili 知名音乐UP主",
    "officialType": "0",
    "opusCount": "2",
    "playCount": "29.70w",
    "profession": null,
    "rankPosition": 639,
    "sex": "男",
    "type": "音乐",
    "videoReviewCount": "2001"
  },
  {
    "coinCount": "6638",
    "face": "https://i1.hdslb.com/bfs/face/9583c2c1ddd95e2f3ab4b4ea9b3a1d3200b64fda.webp",
    "followerDiff": "5041",
    "isCollect": null,
    "level": "6",
    "likeCount": "2.21w",
    "maxSex": null,
    "mid": "36081646",
    "name": "洛天依",
    "newrankIndex": "861.5",
    "officialTitle": "洛天依官方账号",
    "officialType": "0",
    "opusCount": "2",
    "playCount": "7.25w",
    "profession": null,
    "rankPosition": 673,
    "sex": "女",
    "type": "音乐",
    "videoReviewCount": "367"
  },
  {
    "coinCount": "8643",
    "face": "https://i1.hdslb.com/bfs/face/a030f22e9b9ecc044f38d64b5800a1b9d31f5a91.jpg",
    "followerDiff": "1304",
    "isCollect": null,
    "level": "6",
    "likeCount": "2.81w",
    "maxSex": null,
    "mid": "3046429",
    "name": "祖娅纳惜",
    "newrankIndex": "859.8",
    "officialTitle": "bilibili 2020百大UP主、知名UP主、直播高能主播",
    "officialType": "0",
    "opusCount": "1",
    "playCount": "14.28w",
    "profession": null,
    "rankPosition": 695,
    "sex": "女",
    "type": "音乐",
    "videoReviewCount": "329"
  },
  {
    "coinCount": "7.88w",
    "face": "https://i0.hdslb.com/bfs/face/f6c792ebc8d09ce4165207cb29c99474f6bd26e1.jpg",
    "followerDiff": "1101",
    "isCollect": null,
    "level": "4",
    "likeCount": "19.25w",
    "maxSex": null,
    "mid": "1651436400",
    "name": "行走的CD机",
    "newrankIndex": "856.8",
    "officialTitle": "音乐区自制栏目官方账号认证",
    "officialType": "1",
    "opusCount": "2",
    "playCount": "278.85w",
    "profession": null,
    "rankPosition": 739,
    "sex": "保密",
    "type": "音乐",
    "videoReviewCount": "2.64w"
  },
  {
    "coinCount": "2714",
    "face": "https://i2.hdslb.com/bfs/face/cf7d61766d0b48be0724cec3ae857ba086f29f84.jpg",
    "followerDiff": "2275",
    "isCollect": null,
    "level": "6",
    "likeCount": "5.70w",
    "maxSex": null,
    "mid": "298668059",
    "name": "嘻笑堂",
    "newrankIndex": "851.4",
    "officialTitle": "嘻笑堂官方账号，音乐类视频自媒体",
    "officialType": "0",
    "opusCount": "33",
    "playCount": "318.49w",
    "profession": null,
    "rankPosition": 796,
    "sex": "男",
    "type": "音乐",
    "videoReviewCount": "2794"
  },
  {
    "coinCount": "2140",
    "face": "https://i2.hdslb.com/bfs/face/7ddc94b71499d57906afeda1da81d2922fe8627f.jpg",
    "followerDiff": "1912",
    "isCollect": null,
    "level": "6",
    "likeCount": "7496",
    "maxSex": null,
    "mid": "78110942",
    "name": "耳朵听了能怀孕",
    "newrankIndex": "846.8",
    "officialTitle": "bilibili 知名音乐UP主",
    "officialType": "0",
    "opusCount": "1",
    "playCount": "20.49w",
    "profession": null,
    "rankPosition": 854,
    "sex": "保密",
    "type": "音乐",
    "videoReviewCount": "7713"
  },
  {
    "coinCount": "1.19w",
    "face": "https://i0.hdslb.com/bfs/face/3558e4817a00d78d5345c54ec6a17bb3dbda5f7a.jpg",
    "followerDiff": "2079",
    "isCollect": null,
    "level": "6",
    "likeCount": "1.92w",
    "maxSex": null,
    "mid": "23340150",
    "name": "ProjectMili",
    "newrankIndex": "846.3",
    "officialTitle": "Mili官方账号",
    "officialType": "0",
    "opusCount": "1",
    "playCount": "14.13w",
    "profession": null,
    "rankPosition": 865,
    "sex": "保密",
    "type": "音乐",
    "videoReviewCount": "621"
  },
  {
    "coinCount": "2779",
    "face": "https://i2.hdslb.com/bfs/face/759cf0b8678fad30c73426a9d000598380fa6e14.jpg",
    "followerDiff": "5.01w",
    "isCollect": null,
    "level": "6",
    "likeCount": "1.87w",
    "maxSex": null,
    "mid": "1136087954",
    "name": "软月月-疯狂减脂版",
    "newrankIndex": "845.8",
    "officialTitle": "bilibili 知名音乐UP主",
    "officialType": "0",
    "opusCount": "5",
    "playCount": "49.68w",
    "profession": null,
    "rankPosition": 875,
    "sex": "女",
    "type": "音乐",
    "videoReviewCount": "404"
  },
  {
    "coinCount": "3339",
    "face": "https://i1.hdslb.com/bfs/face/ee1fd70a2281f9631ef70e404471cf5f1ac58e82.jpg",
    "followerDiff": "1.30w",
    "isCollect": null,
    "level": "6",
    "likeCount": "19.89w",
    "maxSex": null,
    "mid": "1368498772",
    "name": "你哇哥233",
    "newrankIndex": "845.5",
    "officialTitle": "",
    "officialType": "-1",
    "opusCount": "1",
    "playCount": "153.26w",
    "profession": null,
    "rankPosition": 881,
    "sex": "保密",
    "type": "音乐",
    "videoReviewCount": "375"
  },
  {
    "coinCount": "2416",
    "face": "https://i1.hdslb.com/bfs/face/c0633737a7d7d7a2b53cd682eda4dc7c5b509247.jpg",
    "followerDiff": "2859",
    "isCollect": null,
    "level": "6",
    "likeCount": "3.29w",
    "maxSex": null,
    "mid": "17134369",
    "name": "司墨尧smile",
    "newrankIndex": "843.8",
    "officialTitle": "bilibili 2022百大UP主、音乐人司墨尧smile",
    "officialType": "0",
    "opusCount": "1",
    "playCount": "29.97w",
    "profession": null,
    "rankPosition": 904,
    "sex": "女",
    "type": "音乐",
    "videoReviewCount": "357"
  },
  {
    "coinCount": "1278",
    "face": "https://i2.hdslb.com/bfs/face/39c9ff3f57d8c3624936b452618ad5b15e90467b.jpg",
    "followerDiff": "1.45w",
    "isCollect": null,
    "level": "6",
    "likeCount": "9.30w",
    "maxSex": null,
    "mid": "532769633",
    "name": "VicetoneMusic",
    "newrankIndex": "839.7",
    "officialTitle": "Vicetone官方账号",
    "officialType": "0",
    "opusCount": "2",
    "playCount": "59.14w",
    "profession": null,
    "rankPosition": 948,
    "sex": "男",
    "type": "音乐",
    "videoReviewCount": "813"
  },
  {
    "coinCount": "5754",
    "face": "https://i2.hdslb.com/bfs/face/fc1e5aeeeb29c661c4f665cb089f2939c9b159c7.jpg",
    "followerDiff": "5314",
    "isCollect": null,
    "level": "6",
    "likeCount": "1.69w",
    "maxSex": null,
    "mid": "210752",
    "name": "真栗",
    "newrankIndex": "838.9",
    "officialTitle": "bilibili 知名UP主",
    "officialType": "0",
    "opusCount": "1",
    "playCount": "31.04w",
    "profession": null,
    "rankPosition": 968,
    "sex": "女",
    "type": "音乐",
    "videoReviewCount": "382"
  },
  {
    "coinCount": "4649",
    "face": "https://i1.hdslb.com/bfs/face/7a576f8cb6354f29de63c407ac2ccc3d51f12751.jpg",
    "followerDiff": "4383",
    "isCollect": null,
    "level": "6",
    "likeCount": "8.72w",
    "maxSex": null,
    "mid": "3493087382866600",
    "name": "JayMe官方粉丝社区",
    "newrankIndex": "838.2",
    "officialTitle": "周杰伦官方粉丝社区官方账号",
    "officialType": "1",
    "opusCount": "70",
    "playCount": "265.85w",
    "profession": null,
    "rankPosition": 980,
    "sex": "男",
    "type": "音乐",
    "videoReviewCount": "2122"
  },
  {
    "coinCount": "5593",
    "face": "https://i1.hdslb.com/bfs/face/a6e4e111fae3c43533e382b08e0e83577df881c5.jpg",
    "followerDiff": "3398",
    "isCollect": null,
    "level": "6",
    "likeCount": "2.08w",
    "maxSex": null,
    "mid": "2115962425",
    "name": "NMIXX",
    "newrankIndex": "835.5",
    "officialTitle": "JYPE旗下女子组合NMIXX官方账号",
    "officialType": "0",
    "opusCount": "3",
    "playCount": "19.94w",
    "profession": null,
    "rankPosition": 1024,
    "sex": "女",
    "type": "音乐",
    "videoReviewCount": "2093"
  },
  {
    "coinCount": "5561",
    "face": "https://i0.hdslb.com/bfs/face/92f8ed5d5111152e14e73d6395ca3eb441aa4dd9.jpg",
    "followerDiff": "1.02w",
    "isCollect": null,
    "level": "6",
    "likeCount": "1.69w",
    "maxSex": null,
    "mid": "293229600",
    "name": "Ray叔爱唱歌",
    "newrankIndex": "833.8",
    "officialTitle": "bilibili 知名音乐UP主",
    "officialType": "0",
    "opusCount": "1",
    "playCount": "29.14w",
    "profession": null,
    "rankPosition": 1046,
    "sex": "保密",
    "type": "音乐",
    "videoReviewCount": "1391"
  },
  {
    "coinCount": "1680",
    "face": "https://i0.hdslb.com/bfs/face/7a07a93774854ce0a3b54bcd9ecf703b63652014.jpg",
    "followerDiff": "3493",
    "isCollect": null,
    "level": "6",
    "likeCount": "2.56w",
    "maxSex": null,
    "mid": "2128487337",
    "name": "aespa",
    "newrankIndex": "832.6",
    "officialTitle": "女子组合aespa官方账号",
    "officialType": "0",
    "opusCount": "5",
    "playCount": "35.59w",
    "profession": null,
    "rankPosition": 1071,
    "sex": "保密",
    "type": "音乐",
    "videoReviewCount": "3442"
  },
  {
    "coinCount": "3850",
    "face": "https://i1.hdslb.com/bfs/face/d3e276ec2a3f27ddc45360cf09978f7a2a61fbf3.jpg",
    "followerDiff": "7164",
    "isCollect": null,
    "level": "6",
    "likeCount": "2.19w",
    "maxSex": null,
    "mid": "385287865",
    "name": "俄罗斯指弹大叔Igor",
    "newrankIndex": "832.3",
    "officialTitle": "俄罗斯指弹大师 Igor Presnyakov官方账号",
    "officialType": "0",
    "opusCount": "1",
    "playCount": "24.83w",
    "profession": null,
    "rankPosition": 1077,
    "sex": "男",
    "type": "音乐",
    "videoReviewCount": "415"
  },
  {
    "coinCount": "8433",
    "face": "https://i1.hdslb.com/bfs/face/6003c64d4cd7cb07b7f4f400b0a8989af8515399.jpg",
    "followerDiff": "2530",
    "isCollect": null,
    "level": "6",
    "likeCount": "2.15w",
    "maxSex": null,
    "mid": "501005668",
    "name": "黄霄雲",
    "newrankIndex": "830.7",
    "officialTitle": "歌手，演员黄霄雲",
    "officialType": "0",
    "opusCount": "4",
    "playCount": "18.89w",
    "profession": null,
    "rankPosition": 1103,
    "sex": "保密",
    "type": "音乐",
    "videoReviewCount": "725"
  },
  {
    "coinCount": "1119",
    "face": "https://i1.hdslb.com/bfs/face/b1b0779b1af9d934fef52d6d77bf20ba1655aaed.jpg",
    "followerDiff": "3443",
    "isCollect": null,
    "level": "6",
    "likeCount": "4.27w",
    "maxSex": null,
    "mid": "193262326",
    "name": "音乐Wu哥",
    "newrankIndex": "830.3",
    "officialTitle": "bilibili 知名音乐UP主",
    "officialType": "0",
    "opusCount": "7",
    "playCount": "100.19w",
    "profession": null,
    "rankPosition": 1108,
    "sex": "男",
    "type": "音乐",
    "videoReviewCount": "2403"
  },
  {
    "coinCount": "7851",
    "face": "https://i1.hdslb.com/bfs/face/3f47a20c74d4b1b2b01a6ed538f0cd6b7f92d7dd.jpg",
    "followerDiff": "4247",
    "isCollect": null,
    "level": "6",
    "likeCount": "2.65w",
    "maxSex": null,
    "mid": "19565962",
    "name": "星粥Kayuu",
    "newrankIndex": "828.5",
    "officialTitle": "bilibili 知名虚拟UP主、直播高能主播",
    "officialType": "0",
    "opusCount": "2",
    "playCount": "19.14w",
    "profession": null,
    "rankPosition": 1134,
    "sex": "女",
    "type": "音乐",
    "videoReviewCount": "146"
  },
  {
    "coinCount": "1717",
    "face": "https://i2.hdslb.com/bfs/face/c11e4618ccc9ff397d66a1e05e45715d108ad78c.jpg",
    "followerDiff": "6884",
    "isCollect": null,
    "level": "6",
    "likeCount": "2.25w",
    "maxSex": null,
    "mid": "331480256",
    "name": "音乐影视馆",
    "newrankIndex": "825.3",
    "officialTitle": "",
    "officialType": "-1",
    "opusCount": "3",
    "playCount": "43.73w",
    "profession": null,
    "rankPosition": 1193,
    "sex": "男",
    "type": "音乐",
    "videoReviewCount": "2883"
  },
  {
    "coinCount": "6672",
    "face": "https://i1.hdslb.com/bfs/face/1a247649adc3a33f4322b6fbf59ccffa6860f275.jpg",
    "followerDiff": "1657",
    "isCollect": null,
    "level": "6",
    "likeCount": "2.56w",
    "maxSex": null,
    "mid": "1734978373",
    "name": "小柔Channel",
    "newrankIndex": "824.1",
    "officialTitle": "bilibili 知名虚拟UP主、直播高能主播",
    "officialType": "0",
    "opusCount": "6",
    "playCount": "20.28w",
    "profession": null,
    "rankPosition": 1217,
    "sex": "保密",
    "type": "音乐",
    "videoReviewCount": "577"
  },
  {
    "coinCount": "6547",
    "face": "https://i1.hdslb.com/bfs/face/3dd2f469e1a6240f4d37dbfde9578ba6033acb68.jpg",
    "followerDiff": "4703",
    "isCollect": null,
    "level": "6",
    "likeCount": "1.40w",
    "maxSex": null,
    "mid": "339885439",
    "name": "是小钱-",
    "newrankIndex": "823.6",
    "officialTitle": "bilibili 知名音乐UP主",
    "officialType": "0",
    "opusCount": "1",
    "playCount": "14.61w",
    "profession": null,
    "rankPosition": 1221,
    "sex": "女",
    "type": "音乐",
    "videoReviewCount": "221"
  },
  {
    "coinCount": "1.19w",
    "face": "https://i1.hdslb.com/bfs/face/dcc2fe995969526f7f69065d7ca19a1a9e5f6e1c.jpg",
    "followerDiff": "861",
    "isCollect": null,
    "level": "6",
    "likeCount": "3.82w",
    "maxSex": null,
    "mid": "4786825",
    "name": "沧弦落尘",
    "newrankIndex": "822.4",
    "officialTitle": "",
    "officialType": "-1",
    "opusCount": "1",
    "playCount": "32.54w",
    "profession": null,
    "rankPosition": 1244,
    "sex": "男",
    "type": "音乐",
    "videoReviewCount": "391"
  },
  {
    "coinCount": "1723",
    "face": "https://i0.hdslb.com/bfs/face/10471a715819e623c8fae8d7cbdc917df2adf754.jpg",
    "followerDiff": "2.28w",
    "isCollect": null,
    "level": "6",
    "likeCount": "4.59w",
    "maxSex": null,
    "mid": "690111567",
    "name": "鱼酱_是这样说的",
    "newrankIndex": "821.1",
    "officialTitle": "",
    "officialType": "-1",
    "opusCount": "3",
    "playCount": "23.74w",
    "profession": null,
    "rankPosition": 1266,
    "sex": "女",
    "type": "音乐",
    "videoReviewCount": "119"
  },
  {
    "coinCount": "2272",
    "face": "https://i2.hdslb.com/bfs/face/161944ef43a9e3d075048bdbfe40172d4f4faa66.jpg",
    "followerDiff": "2795",
    "isCollect": null,
    "level": "6",
    "likeCount": "5.31w",
    "maxSex": null,
    "mid": "30554651",
    "name": "丁克森絮絮叨叨刀刀刀",
    "newrankIndex": "820.6",
    "officialTitle": "音乐人丁克森絮絮叨叨刀刀刀",
    "officialType": "0",
    "opusCount": "6",
    "playCount": "105.43w",
    "profession": null,
    "rankPosition": 1273,
    "sex": "男",
    "type": "音乐",
    "videoReviewCount": "475"
  },
  {
    "coinCount": "1552",
    "face": "https://i2.hdslb.com/bfs/face/c2c90016c0684576321c1753a99cbb35851d20d6.jpg",
    "followerDiff": "930",
    "isCollect": null,
    "level": "6",
    "likeCount": "4.86w",
    "maxSex": null,
    "mid": "419085137",
    "name": "爱豆安利所",
    "newrankIndex": "817.7",
    "officialTitle": "",
    "officialType": "-1",
    "opusCount": "172",
    "playCount": "123.55w",
    "profession": null,
    "rankPosition": 1331,
    "sex": "保密",
    "type": "音乐",
    "videoReviewCount": "2427"
  },
  {
    "coinCount": "5369",
    "face": "https://i0.hdslb.com/bfs/face/007e654ca092c1cd93bd01a822f701e06b858570.jpg",
    "followerDiff": "1681",
    "isCollect": null,
    "level": "6",
    "likeCount": "1.69w",
    "maxSex": null,
    "mid": "673376925",
    "name": "NCTDREAM",
    "newrankIndex": "817.5",
    "officialTitle": "男子偶像组合NCTDREAM官方账号",
    "officialType": "0",
    "opusCount": "2",
    "playCount": "15.46w",
    "profession": null,
    "rankPosition": 1335,
    "sex": "保密",
    "type": "音乐",
    "videoReviewCount": "696"
  },
  {
    "coinCount": "1766",
    "face": "https://i1.hdslb.com/bfs/face/71b6cb14cf1ec3fcba4f03f33a53a4928aebe8c3.jpg",
    "followerDiff": "5633",
    "isCollect": null,
    "level": "6",
    "likeCount": "7.77w",
    "maxSex": null,
    "mid": "2092325170",
    "name": "Rc过山车人声乐团",
    "newrankIndex": "813.4",
    "officialTitle": "bilibili 知名音乐UP主",
    "officialType": "0",
    "opusCount": "2",
    "playCount": "42.54w",
    "profession": null,
    "rankPosition": 1429,
    "sex": "女",
    "type": "音乐",
    "videoReviewCount": "147"
  },
  {
    "coinCount": "1.23w",
    "face": "https://i1.hdslb.com/bfs/face/da5dca680d0614d3a276cc57afd3feba6974c656.jpg",
    "followerDiff": "7536",
    "isCollect": null,
    "level": "6",
    "likeCount": "2.36w",
    "maxSex": null,
    "mid": "1920628",
    "name": "夜吟月寒丶",
    "newrankIndex": "813.3",
    "officialTitle": "",
    "officialType": "-1",
    "opusCount": "2",
    "playCount": "43.84w",
    "profession": null,
    "rankPosition": 1430,
    "sex": "男",
    "type": "音乐",
    "videoReviewCount": "309"
  },
  {
    "coinCount": "2.21w",
    "face": "https://i1.hdslb.com/bfs/face/2200677186d68d5a9780366b8abf79750be796ef.jpg",
    "followerDiff": "1078",
    "isCollect": null,
    "level": "6",
    "likeCount": "5.41w",
    "maxSex": null,
    "mid": "7949629",
    "name": "輕鸞軸心",
    "newrankIndex": "812.7",
    "officialTitle": "",
    "officialType": "-1",
    "opusCount": "1",
    "playCount": "37.13w",
    "profession": null,
    "rankPosition": 1449,
    "sex": "男",
    "type": "音乐",
    "videoReviewCount": "313"
  },
  {
    "coinCount": "2057",
    "face": "https://i2.hdslb.com/bfs/face/a2ae57e3fe7176d252a9ecd096cd15137a7e0df7.gif",
    "followerDiff": "3275",
    "isCollect": null,
    "level": "6",
    "likeCount": "2.44w",
    "maxSex": null,
    "mid": "702929",
    "name": "XIANVXIA",
    "newrankIndex": "812.4",
    "officialTitle": "",
    "officialType": "-1",
    "opusCount": "22",
    "playCount": "41.98w",
    "profession": null,
    "rankPosition": 1455,
    "sex": "女",
    "type": "音乐",
    "videoReviewCount": "1155"
  },
  {
    "coinCount": "4197",
    "face": "https://i0.hdslb.com/bfs/face/c78aa9059a803fa68b8909e293a27c5962f67634.jpg",
    "followerDiff": "5759",
    "isCollect": null,
    "level": "6",
    "likeCount": "1.10w",
    "maxSex": null,
    "mid": "37880130",
    "name": "玩音乐的EZ",
    "newrankIndex": "812.0",
    "officialTitle": "bilibili 知名音乐UP主",
    "officialType": "0",
    "opusCount": "2",
    "playCount": "12.95w",
    "profession": null,
    "rankPosition": 1466,
    "sex": "男",
    "type": "音乐",
    "videoReviewCount": "176"
  },
  {
    "coinCount": "7105",
    "face": "https://i2.hdslb.com/bfs/face/a7e23ce7d888ec50016eb76a64a01ac36570bcb6.jpg",
    "followerDiff": "2809",
    "isCollect": null,
    "level": "6",
    "likeCount": "1.41w",
    "maxSex": null,
    "mid": "197703608",
    "name": "王朝1982",
    "newrankIndex": "808.9",
    "officialTitle": "bilibili 音乐人",
    "officialType": "0",
    "opusCount": "1",
    "playCount": "8.84w",
    "profession": null,
    "rankPosition": 1520,
    "sex": "男",
    "type": "音乐",
    "videoReviewCount": "192"
  },
  {
    "coinCount": "3748",
    "face": "https://i0.hdslb.com/bfs/face/4c692acec4092588975bcb24be646166bc24ae31.jpg",
    "followerDiff": "1460",
    "isCollect": null,
    "level": "6",
    "likeCount": "3.04w",
    "maxSex": null,
    "mid": "1185017133",
    "name": "ITZY",
    "newrankIndex": "805.7",
    "officialTitle": "JYPE旗下女子组合ITZY官方账号",
    "officialType": "0",
    "opusCount": "6",
    "playCount": "12.99w",
    "profession": null,
    "rankPosition": 1587,
    "sex": "女",
    "type": "音乐",
    "videoReviewCount": "449"
  },
  {
    "coinCount": "3588",
    "face": "https://i2.hdslb.com/bfs/face/39869a62173b8ac15334d3ed31b24e02f3b86a7a.jpg",
    "followerDiff": "2690",
    "isCollect": null,
    "level": "6",
    "likeCount": "1.51w",
    "maxSex": null,
    "mid": "30279665",
    "name": "theiaの阿旋酱",
    "newrankIndex": "805.2",
    "officialTitle": "bilibili 知名音乐UP主",
    "officialType": "0",
    "opusCount": "1",
    "playCount": "22.37w",
    "profession": null,
    "rankPosition": 1594,
    "sex": "保密",
    "type": "音乐",
    "videoReviewCount": "117"
  },
  {
    "coinCount": "4816",
    "face": "https://i1.hdslb.com/bfs/face/d4cd30e434e52601ff2a18c32853f2ba032716f9.jpg",
    "followerDiff": "2271",
    "isCollect": null,
    "level": "6",
    "likeCount": "3.07w",
    "maxSex": null,
    "mid": "1286729425",
    "name": "小k-音乐",
    "newrankIndex": "803.4",
    "officialTitle": "",
    "officialType": "-1",
    "opusCount": "6",
    "playCount": "87.41w",
    "profession": null,
    "rankPosition": 1633,
    "sex": "男",
    "type": "音乐",
    "videoReviewCount": "616"
  },
  {
    "coinCount": "1914",
    "face": "https://i2.hdslb.com/bfs/face/2c391972a4fba63e47169beb759d38da492163fe.jpg",
    "followerDiff": "3.66w",
    "isCollect": null,
    "level": "6",
    "likeCount": "9223",
    "maxSex": null,
    "mid": "1839002753",
    "name": "鹿火CAVY",
    "newrankIndex": "801.5",
    "officialTitle": "bilibili 知名音乐UP主、直播高能主播",
    "officialType": "0",
    "opusCount": "1",
    "playCount": "15.80w",
    "profession": null,
    "rankPosition": 1676,
    "sex": "女",
    "type": "音乐",
    "videoReviewCount": "322"
  },
  {
    "coinCount": "2475",
    "face": "https://i2.hdslb.com/bfs/face/db60ce9a5c30079f595e2953f2667babbc152dd7.jpg",
    "followerDiff": "3120",
    "isCollect": null,
    "level": "6",
    "likeCount": "6563",
    "maxSex": null,
    "mid": "1691501735",
    "name": "极致音乐汇",
    "newrankIndex": "801.1",
    "officialTitle": "",
    "officialType": "-1",
    "opusCount": "3",
    "playCount": "16.36w",
    "profession": null,
    "rankPosition": 1681,
    "sex": "保密",
    "type": "音乐",
    "videoReviewCount": "460"
  },
  {
    "coinCount": "1.04w",
    "face": "https://i0.hdslb.com/bfs/face/4282e46ce9de747f3b40335c68319c9a86dcb98b.jpg",
    "followerDiff": "278",
    "isCollect": null,
    "level": "6",
    "likeCount": "1.36w",
    "maxSex": null,
    "mid": "32304711",
    "name": "杜鑫一",
    "newrankIndex": "799.9",
    "officialTitle": "",
    "officialType": "-1",
    "opusCount": "5",
    "playCount": "10.50w",
    "profession": null,
    "rankPosition": 1713,
    "sex": "男",
    "type": "音乐",
    "videoReviewCount": "1.08w"
  },
  {
    "coinCount": "2947",
    "face": "https://i1.hdslb.com/bfs/face/a83b296101bb36a6f1dacb8fdfa74a57a2c29445.jpg",
    "followerDiff": "2570",
    "isCollect": null,
    "level": "6",
    "likeCount": "1.01w",
    "maxSex": null,
    "mid": "1856528671",
    "name": "陆鳐LuLu",
    "newrankIndex": "798.5",
    "officialTitle": "bilibili 知名音乐UP主",
    "officialType": "0",
    "opusCount": "1",
    "playCount": "9.45w",
    "profession": null,
    "rankPosition": 1740,
    "sex": "女",
    "type": "音乐",
    "videoReviewCount": "232"
  },
  {
    "coinCount": "3309",
    "face": "https://i2.hdslb.com/bfs/face/27c99c000e6c2c0761526090450b3be29cdeb77f.jpg",
    "followerDiff": "943",
    "isCollect": null,
    "level": "6",
    "likeCount": "2.81w",
    "maxSex": null,
    "mid": "31596887",
    "name": "羊小星",
    "newrankIndex": "795.4",
    "officialTitle": "bilibili 知名UP主",
    "officialType": "0",
    "opusCount": "3",
    "playCount": "17.91w",
    "profession": null,
    "rankPosition": 1784,
    "sex": "男",
    "type": "音乐",
    "videoReviewCount": "222"
  },
  {
    "coinCount": "5256",
    "face": "https://i0.hdslb.com/bfs/face/07df2da19aec181d7db883c91618f60a1841e346.jpg",
    "followerDiff": "3191",
    "isCollect": null,
    "level": "6",
    "likeCount": "4.17w",
    "maxSex": null,
    "mid": "414763170",
    "name": "土法炼钢队",
    "newrankIndex": "793.7",
    "officialTitle": "bilibili 知名音乐UP主",
    "officialType": "0",
    "opusCount": "3",
    "playCount": "18.18w",
    "profession": null,
    "rankPosition": 1819,
    "sex": "男",
    "type": "音乐",
    "videoReviewCount": "115"
  },
  {
    "coinCount": "1857",
    "face": "https://i2.hdslb.com/bfs/face/739613f8787e7def3a54ff6e4f0d44494f6252bf.jpg",
    "followerDiff": "3078",
    "isCollect": null,
    "level": "6",
    "likeCount": "2.64w",
    "maxSex": null,
    "mid": "15960317",
    "name": "碰碰彭碰彭",
    "newrankIndex": "792.5",
    "officialTitle": "bilibili 2022百大UP主、知名音乐UP主",
    "officialType": "0",
    "opusCount": "1",
    "playCount": "27.15w",
    "profession": null,
    "rankPosition": 1846,
    "sex": "女",
    "type": "音乐",
    "videoReviewCount": "276"
  },
  {
    "coinCount": "1642",
    "face": "https://i2.hdslb.com/bfs/face/e6c83e92c8c2b5af89c64eea3acbc328c8e4eca1.jpg",
    "followerDiff": "1.29w",
    "isCollect": null,
    "level": "6",
    "likeCount": "8774",
    "maxSex": null,
    "mid": "399918500",
    "name": "初音未来_Crypton",
    "newrankIndex": "789.0",
    "officialTitle": "日本虚拟歌手，初音未来官方账号",
    "officialType": "0",
    "opusCount": "1",
    "playCount": "2.42w",
    "profession": null,
    "rankPosition": 1918,
    "sex": "女",
    "type": "音乐",
    "videoReviewCount": "64"
  },
  {
    "coinCount": "5242",
    "face": "https://i1.hdslb.com/bfs/face/be19e7e176f474fc96ce249039ff8aa5259192a5.jpg",
    "followerDiff": "620",
    "isCollect": null,
    "level": "6",
    "likeCount": "1.96w",
    "maxSex": null,
    "mid": "12355462",
    "name": "鬼面P",
    "newrankIndex": "788.8",
    "officialTitle": "音乐人鬼面p",
    "officialType": "0",
    "opusCount": "8",
    "playCount": "8.30w",
    "profession": null,
    "rankPosition": 1923,
    "sex": "男",
    "type": "音乐",
    "videoReviewCount": "1128"
  },
  {
    "coinCount": "2768",
    "face": "https://i1.hdslb.com/bfs/face/007d045f1ad77a80c94b84c18f1bf20f9669c39a.jpg",
    "followerDiff": "1.93w",
    "isCollect": null,
    "level": "6",
    "likeCount": "1.04w",
    "maxSex": null,
    "mid": "3494351384611564",
    "name": "阿久_Aku",
    "newrankIndex": "788.2",
    "officialTitle": "",
    "officialType": "-1",
    "opusCount": "1",
    "playCount": "5.89w",
    "profession": null,
    "rankPosition": 1933,
    "sex": "保密",
    "type": "音乐",
    "videoReviewCount": "165"
  },
  {
    "coinCount": "8168",
    "face": "https://i1.hdslb.com/bfs/face/69756c667355d24e8a24dd1f396fdd53dee0a4b4.jpg",
    "followerDiff": "432",
    "isCollect": null,
    "level": "6",
    "likeCount": "9606",
    "maxSex": null,
    "mid": "2765893",
    "name": "恰空_PurrLude",
    "newrankIndex": "787.1",
    "officialTitle": "bilibili 知名音乐UP主",
    "officialType": "0",
    "opusCount": "1",
    "playCount": "6.53w",
    "profession": null,
    "rankPosition": 1953,
    "sex": "保密",
    "type": "音乐",
    "videoReviewCount": "850"
  },
  {
    "coinCount": "4884",
    "face": "https://i1.hdslb.com/bfs/face/d9e869c462bdb5b952027466b95941e30521069b.jpg",
    "followerDiff": "760",
    "isCollect": null,
    "level": "6",
    "likeCount": "6721",
    "maxSex": null,
    "mid": "324516490",
    "name": "漫行PD",
    "newrankIndex": "786.4",
    "officialTitle": "bilibili 知名音乐UP主",
    "officialType": "0",
    "opusCount": "1",
    "playCount": "7.80w",
    "profession": null,
    "rankPosition": 1969,
    "sex": "保密",
    "type": "音乐",
    "videoReviewCount": "1994"
  },
  {
    "coinCount": "1829",
    "face": "https://i0.hdslb.com/bfs/face/8ec7287261962f1ab827bfe524ee7107cad7893e.jpg",
    "followerDiff": "1.20w",
    "isCollect": null,
    "level": "6",
    "likeCount": "1.72w",
    "maxSex": null,
    "mid": "1995076299",
    "name": "哔哔啵啵璇",
    "newrankIndex": "785.6",
    "officialTitle": "bilibili 音乐人",
    "officialType": "0",
    "opusCount": "4",
    "playCount": "16.88w",
    "profession": null,
    "rankPosition": 1989,
    "sex": "女",
    "type": "音乐",
    "videoReviewCount": "196"
  },
  {
    "coinCount": "2648",
    "face": "https://i0.hdslb.com/bfs/face/86244571e42d360e8144431301e257051057b0b4.jpg",
    "followerDiff": "3745",
    "isCollect": null,
    "level": "6",
    "likeCount": "6953",
    "maxSex": null,
    "mid": "12948552",
    "name": "六的月",
    "newrankIndex": "784.6",
    "officialTitle": "",
    "officialType": "-1",
    "opusCount": "2",
    "playCount": "12.28w",
    "profession": null,
    "rankPosition": 2015,
    "sex": "保密",
    "type": "音乐",
    "videoReviewCount": "1150"
  },
  {
    "coinCount": "2.21w",
    "face": "https://i0.hdslb.com/bfs/face/11fb2bdf6983005cc93ce5e3c6b4ae421791dc58.jpg",
    "followerDiff": "543",
    "isCollect": null,
    "level": "6",
    "likeCount": "5.42w",
    "maxSex": null,
    "mid": "823284",
    "name": "向晚的狗丶鱼谷",
    "newrankIndex": "784.3",
    "officialTitle": "",
    "officialType": "-1",
    "opusCount": "2",
    "playCount": "37.20w",
    "profession": null,
    "rankPosition": 2021,
    "sex": "男",
    "type": "音乐",
    "videoReviewCount": "313"
  },
  {
    "coinCount": "3945",
    "face": "https://i2.hdslb.com/bfs/face/28fac9ebad9cb6f2fe7628a219c08f98cff39816.jpg",
    "followerDiff": "1023",
    "isCollect": null,
    "level": "6",
    "likeCount": "8165",
    "maxSex": null,
    "mid": "690545051",
    "name": "吹拉弹唱慕星银",
    "newrankIndex": "781.4",
    "officialTitle": "bilibili 知名音乐UP主",
    "officialType": "0",
    "opusCount": "1",
    "playCount": "11.21w",
    "profession": null,
    "rankPosition": 2107,
    "sex": "女",
    "type": "音乐",
    "videoReviewCount": "408"
  },
  {
    "coinCount": "4884",
    "face": "https://i1.hdslb.com/bfs/face/1541ab8e28c21b111f5d52e8bce1aa8d5115a0ae.jpg",
    "followerDiff": "2911",
    "isCollect": null,
    "level": "6",
    "likeCount": "7592",
    "maxSex": null,
    "mid": "1966161706",
    "name": "Tank吕建忠",
    "newrankIndex": "778.2",
    "officialTitle": "歌手 Tank吕建忠",
    "officialType": "0",
    "opusCount": "1",
    "playCount": "11.12w",
    "profession": null,
    "rankPosition": 2184,
    "sex": "男",
    "type": "音乐",
    "videoReviewCount": "517"
  },
  {
    "coinCount": "1359",
    "face": "https://i1.hdslb.com/bfs/face/a83ef0a2515e8fe9ac3e3495ff51eee548a11484.jpg",
    "followerDiff": "7.34w",
    "isCollect": null,
    "level": "5",
    "likeCount": "3.76w",
    "maxSex": null,
    "mid": "1031950747",
    "name": "挖草真帅",
    "newrankIndex": "777.6",
    "officialTitle": "",
    "officialType": "-1",
    "opusCount": "7",
    "playCount": "29.05w",
    "profession": null,
    "rankPosition": 2206,
    "sex": "男",
    "type": "音乐",
    "videoReviewCount": "124"
  },
  {
    "coinCount": "1488",
    "face": "https://i2.hdslb.com/bfs/face/7b3e4df190137cdb3c0d661a2fb769853146c2db.jpg",
    "followerDiff": "1.46w",
    "isCollect": null,
    "level": "3",
    "likeCount": "3.63w",
    "maxSex": null,
    "mid": "1562122091",
    "name": "flower_6Bp1",
    "newrankIndex": "777.1",
    "officialTitle": "",
    "officialType": "-1",
    "opusCount": "3",
    "playCount": "26.15w",
    "profession": null,
    "rankPosition": 2215,
    "sex": "保密",
    "type": "音乐",
    "videoReviewCount": "358"
  },
  {
    "coinCount": "4396",
    "face": "https://i0.hdslb.com/bfs/face/d442b405ea18f1fff815084a73fe3a3abb5c1424.gif",
    "followerDiff": "337",
    "isCollect": null,
    "level": "6",
    "likeCount": "8739",
    "maxSex": null,
    "mid": "5055",
    "name": "小缘",
    "newrankIndex": "776.7",
    "officialTitle": "bilibili 2018百大UP主、 知名唱见、直播高能主播",
    "officialType": "0",
    "opusCount": "1",
    "playCount": "17.17w",
    "profession": null,
    "rankPosition": 2220,
    "sex": "女",
    "type": "音乐",
    "videoReviewCount": "130"
  },
  {
    "coinCount": "1425",
    "face": "https://i2.hdslb.com/bfs/face/478f689a1b91d5d9958b35c1d42e3cd6280d3c9f.jpg",
    "followerDiff": "2635",
    "isCollect": null,
    "level": "6",
    "likeCount": "5601",
    "maxSex": null,
    "mid": "3461571609102962",
    "name": "StrayKids",
    "newrankIndex": "773.1",
    "officialTitle": "Stray Kids组合官方账号",
    "officialType": "0",
    "opusCount": "1",
    "playCount": "4.65w",
    "profession": null,
    "rankPosition": 2323,
    "sex": "男",
    "type": "音乐",
    "videoReviewCount": "1390"
  },
  {
    "coinCount": "3659",
    "face": "https://i0.hdslb.com/bfs/face/2b31d8ba5fa6361709c835316ad747a2bdc88a16.jpg",
    "followerDiff": "4577",
    "isCollect": null,
    "level": "6",
    "likeCount": "1.43w",
    "maxSex": null,
    "mid": "18915405",
    "name": "童猪啊i",
    "newrankIndex": "772.9",
    "officialTitle": "",
    "officialType": "-1",
    "opusCount": "4",
    "playCount": "28.67w",
    "profession": null,
    "rankPosition": 2328,
    "sex": "女",
    "type": "音乐",
    "videoReviewCount": "264"
  },
  {
    "coinCount": "2087",
    "face": "https://i2.hdslb.com/bfs/face/1bd7b825c75230f2fbe62a7e0b995e007098073f.jpg",
    "followerDiff": "3491",
    "isCollect": null,
    "level": "6",
    "likeCount": "1.52w",
    "maxSex": null,
    "mid": "1060544882",
    "name": "东洋雪莲",
    "newrankIndex": "772.4",
    "officialTitle": "",
    "officialType": "-1",
    "opusCount": "7",
    "playCount": "14.50w",
    "profession": null,
    "rankPosition": 2340,
    "sex": "保密",
    "type": "音乐",
    "videoReviewCount": "303"
  },
  {
    "coinCount": "1580",
    "face": "https://i0.hdslb.com/bfs/face/f5c1e45e5d44fac08f985f88e9a0ee1123494cfd.jpg",
    "followerDiff": "1508",
    "isCollect": null,
    "level": "6",
    "likeCount": "7444",
    "maxSex": null,
    "mid": "3461564166310872",
    "name": "屾奇",
    "newrankIndex": "770.0",
    "officialTitle": "",
    "officialType": "-1",
    "opusCount": "10",
    "playCount": "12.13w",
    "profession": null,
    "rankPosition": 2416,
    "sex": "男",
    "type": "音乐",
    "videoReviewCount": "1467"
  },
  {
    "coinCount": "5368",
    "face": "https://i0.hdslb.com/bfs/face/98f6be376d7212dd5bad74e91934ad920eec7163.jpg",
    "followerDiff": "333",
    "isCollect": null,
    "level": "6",
    "likeCount": "1.81w",
    "maxSex": null,
    "mid": "698438232",
    "name": "扇宝",
    "newrankIndex": "769.6",
    "officialTitle": "bilibili 知名UP主",
    "officialType": "0",
    "opusCount": "2",
    "playCount": "13.54w",
    "profession": null,
    "rankPosition": 2427,
    "sex": "保密",
    "type": "音乐",
    "videoReviewCount": "357"
  },
  {
    "coinCount": "1657",
    "face": "https://i1.hdslb.com/bfs/face/76b7507ecdb64f4c4208effc7a581803b14593fa.jpg",
    "followerDiff": "4832",
    "isCollect": null,
    "level": "6",
    "likeCount": "6854",
    "maxSex": null,
    "mid": "352117879",
    "name": "Eternity丨L",
    "newrankIndex": "766.7",
    "officialTitle": "",
    "officialType": "-1",
    "opusCount": "4",
    "playCount": "15.05w",
    "profession": null,
    "rankPosition": 2528,
    "sex": "男",
    "type": "音乐",
    "videoReviewCount": "547"
  },
  {
    "coinCount": "1821",
    "face": "https://i0.hdslb.com/bfs/face/ab3e788c3e9f381c8367560f9c0c192b3da00a58.jpg",
    "followerDiff": "1759",
    "isCollect": null,
    "level": "6",
    "likeCount": "1.07w",
    "maxSex": null,
    "mid": "1612794",
    "name": "英国小哥KalexWillzy",
    "newrankIndex": "762.6",
    "officialTitle": "英国嘻哈电台Westside主持人",
    "officialType": "0",
    "opusCount": "4",
    "playCount": "32.99w",
    "profession": null,
    "rankPosition": 2652,
    "sex": "男",
    "type": "音乐",
    "videoReviewCount": "1059"
  },
  {
    "coinCount": "1390",
    "face": "http://i0.hdslb.com/bfs/face/54ee56bb37546cd676c35eee5ae72c4d1c97b332.jpg",
    "followerDiff": "557",
    "isCollect": null,
    "level": "6",
    "likeCount": "4278",
    "maxSex": null,
    "mid": "4952737",
    "name": "GaryGates",
    "newrankIndex": "762.6",
    "officialTitle": "",
    "officialType": "-1",
    "opusCount": "1",
    "playCount": "9.15w",
    "profession": null,
    "rankPosition": 2654,
    "sex": "男",
    "type": "音乐",
    "videoReviewCount": "3248"
  },
  {
    "coinCount": "1154",
    "face": "https://i2.hdslb.com/bfs/face/478f0b4dca1ea011f5d7ad8f4d289c86486dbfc9.jpg",
    "followerDiff": "3822",
    "isCollect": null,
    "level": "6",
    "likeCount": "1.23w",
    "maxSex": null,
    "mid": "43272050",
    "name": "穆小泠Official",
    "newrankIndex": "762.0",
    "officialTitle": "bilibili 知名虚拟UP主、直播高能主播",
    "officialType": "0",
    "opusCount": "2",
    "playCount": "10.20w",
    "profession": null,
    "rankPosition": 2669,
    "sex": "女",
    "type": "音乐",
    "videoReviewCount": "65"
  },
  {
    "coinCount": "1922",
    "face": "https://i2.hdslb.com/bfs/face/fe0acb84b42e6c3ca4da66c5f8a5e4ecad0dc88b.jpg",
    "followerDiff": "9227",
    "isCollect": null,
    "level": "6",
    "likeCount": "7250",
    "maxSex": null,
    "mid": "2034122930",
    "name": "我是梅小贱",
    "newrankIndex": "761.8",
    "officialTitle": "",
    "officialType": "-1",
    "opusCount": "2",
    "playCount": "7.57w",
    "profession": null,
    "rankPosition": 2672,
    "sex": "男",
    "type": "音乐",
    "videoReviewCount": "230"
  },
  {
    "coinCount": "3827",
    "face": "http://i2.hdslb.com/bfs/face/10e3563701bc8ef19f45a1b2ae50560befd29eb3.jpg",
    "followerDiff": "1617",
    "isCollect": null,
    "level": "6",
    "likeCount": "4802",
    "maxSex": null,
    "mid": "65754890",
    "name": "表情银行MimikBanka",
    "newrankIndex": "761.1",
    "officialTitle": "音乐人表情银行MimikBanka",
    "officialType": "0",
    "opusCount": "1",
    "playCount": "9.66w",
    "profession": null,
    "rankPosition": 2698,
    "sex": "保密",
    "type": "音乐",
    "videoReviewCount": "2927"
  },
  {
    "coinCount": "593",
    "face": "https://i1.hdslb.com/bfs/face/4be964615e70e18ab469e4403cb0fa320f8d2fdc.jpg",
    "followerDiff": "3808",
    "isCollect": null,
    "level": "6",
    "likeCount": "5526",
    "maxSex": null,
    "mid": "2043250564",
    "name": "4K音乐馆",
    "newrankIndex": "758.4",
    "officialTitle": "",
    "officialType": "-1",
    "opusCount": "3",
    "playCount": "19.88w",
    "profession": null,
    "rankPosition": 2797,
    "sex": "保密",
    "type": "音乐",
    "videoReviewCount": "525"
  },
  {
    "coinCount": "2395",
    "face": "https://i2.hdslb.com/bfs/face/0f8c9a6b7a532609fa1b29bf029513d86977ca03.jpg",
    "followerDiff": "1528",
    "isCollect": null,
    "level": "6",
    "likeCount": "4717",
    "maxSex": null,
    "mid": "2031078527",
    "name": "凌世昊",
    "newrankIndex": "757.5",
    "officialTitle": "bilibili 知名音乐UP主",
    "officialType": "0",
    "opusCount": "1",
    "playCount": "6.77w",
    "profession": null,
    "rankPosition": 2828,
    "sex": "男",
    "type": "音乐",
    "videoReviewCount": "1205"
  },
  {
    "coinCount": "2318",
    "face": "https://i0.hdslb.com/bfs/face/622ac909529bf5909a3882c9e00ce0053a0c673c.jpg",
    "followerDiff": "2175",
    "isCollect": null,
    "level": "6",
    "likeCount": "6345",
    "maxSex": null,
    "mid": "352091301",
    "name": "陶喆的音乐产房",
    "newrankIndex": "757.3",
    "officialTitle": "音乐人陶喆官方账号",
    "officialType": "0",
    "opusCount": "1",
    "playCount": "5.56w",
    "profession": null,
    "rankPosition": 2839,
    "sex": "保密",
    "type": "音乐",
    "videoReviewCount": "911"
  },
  {
    "coinCount": "6191",
    "face": "https://i2.hdslb.com/bfs/face/4f22c2e149d07d6041a7b729226be71bd8b0d056.jpg",
    "followerDiff": "22",
    "isCollect": null,
    "level": "6",
    "likeCount": "1.25w",
    "maxSex": null,
    "mid": "234782",
    "name": "祈Inory",
    "newrankIndex": "756.7",
    "officialTitle": "bilibili 知名音乐UP主、直播高能主播",
    "officialType": "0",
    "opusCount": "2",
    "playCount": "18.74w",
    "profession": null,
    "rankPosition": 2857,
    "sex": "女",
    "type": "音乐",
    "videoReviewCount": "182"
  },
  {
    "coinCount": "6293",
    "face": "https://i0.hdslb.com/bfs/face/e2e78dc51d3976684eaa103d60c5cbeba3f1ad4d.jpg",
    "followerDiff": "394",
    "isCollect": null,
    "level": "6",
    "likeCount": "1.29w",
    "maxSex": null,
    "mid": "24626874",
    "name": "钢镚小豆豆",
    "newrankIndex": "756.6",
    "officialTitle": "bilibili 音乐人",
    "officialType": "0",
    "opusCount": "4",
    "playCount": "9.68w",
    "profession": null,
    "rankPosition": 2861,
    "sex": "保密",
    "type": "音乐",
    "videoReviewCount": "338"
  },
  {
    "coinCount": "2923",
    "face": "https://i0.hdslb.com/bfs/face/d5b69c37cb0b1a300ffa09660b2f8fdcdefb2826.jpg",
    "followerDiff": "3735",
    "isCollect": null,
    "level": "6",
    "likeCount": "7393",
    "maxSex": null,
    "mid": "49922172",
    "name": "正直少年李发卡",
    "newrankIndex": "756.5",
    "officialTitle": "艺人李艺彤",
    "officialType": "0",
    "opusCount": "1",
    "playCount": "5.99w",
    "profession": null,
    "rankPosition": 2866,
    "sex": "保密",
    "type": "音乐",
    "videoReviewCount": "133"
  },
  {
    "coinCount": "1292",
    "face": "https://i2.hdslb.com/bfs/face/eefc7e3b1f81675868e79ac1995b84e1a7e1b32a.jpg",
    "followerDiff": "1665",
    "isCollect": null,
    "level": "6",
    "likeCount": "2.33w",
    "maxSex": null,
    "mid": "334939754",
    "name": "阿卡大文",
    "newrankIndex": "755.9",
    "officialTitle": "bilibili 知名音乐UP主",
    "officialType": "0",
    "opusCount": "6",
    "playCount": "20.70w",
    "profession": null,
    "rankPosition": 2884,
    "sex": "男",
    "type": "音乐",
    "videoReviewCount": "161"
  },
  {
    "coinCount": "947",
    "face": "https://i1.hdslb.com/bfs/face/0659a622d97c1e597dc1ef5cb5b9c0b36b3ad56c.jpg",
    "followerDiff": "2.01w",
    "isCollect": null,
    "level": "5",
    "likeCount": "1.26w",
    "maxSex": null,
    "mid": "494908687",
    "name": "_Daidai_",
    "newrankIndex": "755.9",
    "officialTitle": "",
    "officialType": "-1",
    "opusCount": "10",
    "playCount": "18.32w",
    "profession": null,
    "rankPosition": 2886,
    "sex": "保密",
    "type": "音乐",
    "videoReviewCount": "963"
  }
]
