[
  {
    "coinCount": "3.78w",
    "face": "https://i1.hdslb.com/bfs/face/b6dad37ef0a68341b6e2f84de5e1f9ee02f8365e.jpg",
    "followerDiff": "1.27w",
    "isCollect": null,
    "level": "6",
    "likeCount": "8.85w",
    "maxSex": {
      "count": "0",
      "key": "男",
      "rate": "76.82%"
    },
    "mid": "21837784",
    "name": "阿斗归来了",
    "newrankIndex": "993.9",
    "officialTitle": "bilibili 2020百大UP主、知名影视UP主",
    "officialType": "0",
    "opusCount": "2",
    "playCount": "153.98w",
    "profession": null,
    "rankPosition": 1,
    "sex": "男",
    "type": "影视",
    "videoReviewCount": "1.36w"
  },
  {
    "coinCount": "6.40w",
    "face": "https://i2.hdslb.com/bfs/face/949fd3f0b9fe23703c970d494edc41ae52ee32de.jpg",
    "followerDiff": "1.02w",
    "isCollect": null,
    "level": "6",
    "likeCount": "17.63w",
    "maxSex": {
      "count": "0",
      "key": "男",
      "rate": "65.41%"
    },
    "mid": "10119428",
    "name": "小片片说大片",
    "newrankIndex": "990.2",
    "officialTitle": "bilibili 2022百大UP主、知名影视UP主",
    "officialType": "0",
    "opusCount": "3",
    "playCount": "307.29w",
    "profession": null,
    "rankPosition": 2,
    "sex": "保密",
    "type": "影视",
    "videoReviewCount": "1.14w"
  },
  {
    "coinCount": "3.64w",
    "face": "https://i0.hdslb.com/bfs/face/9d3229d6157767ebe386f37f33d075e348bea07d.jpg",
    "followerDiff": "4.16w",
    "isCollect": null,
    "level": "6",
    "likeCount": "8.72w",
    "maxSex": {
      "count": "0",
      "key": "男",
      "rate": "69.17%"
    },
    "mid": "49246269",
    "name": "大象放映室",
    "newrankIndex": "989.6",
    "officialTitle": "bilibili 2021百大UP主、知名UP主",
    "officialType": "0",
    "opusCount": "2",
    "playCount": "104.21w",
    "profession": null,
    "rankPosition": 3,
    "sex": "保密",
    "type": "影视",
    "videoReviewCount": "5458"
  },
  {
    "coinCount": "9.65w",
    "face": "https://i0.hdslb.com/bfs/face/a915d1a1ff921cd418e74c5711c91b23e2a18c11.jpg",
    "followerDiff": "8828",
    "isCollect": null,
    "level": "6",
    "likeCount": "26.44w",
    "maxSex": {
      "count": "0",
      "key": "女",
      "rate": "50.31%"
    },
    "mid": "5870268",
    "name": "三代鹿人",
    "newrankIndex": "989.4",
    "officialTitle": "bilibili 知名影视UP主",
    "officialType": "0",
    "opusCount": "1",
    "playCount": "300.26w",
    "profession": null,
    "rankPosition": 4,
    "sex": "男",
    "type": "影视",
    "videoReviewCount": "1.29w"
  },
  {
    "coinCount": "2.84w",
    "face": "https://i1.hdslb.com/bfs/face/145226ff2d32d7c99b8ea3591ffec2f38fc9d3d3.jpg",
    "followerDiff": "1.34w",
    "isCollect": null,
    "level": "6",
    "likeCount": "13.30w",
    "maxSex": {
      "count": "0",
      "key": "男",
      "rate": "56.65%"
    },
    "mid": "79061224",
    "name": "刘老师说电影",
    "newrankIndex": "986.7",
    "officialTitle": "bilibili 2020百大UP主、 知名影视UP主",
    "officialType": "0",
    "opusCount": "1",
    "playCount": "287.12w",
    "profession": null,
    "rankPosition": 5,
    "sex": "男",
    "type": "影视",
    "videoReviewCount": "1.01w"
  },
  {
    "coinCount": "3.42w",
    "face": "https://i2.hdslb.com/bfs/face/03c9c018c34cd3630aba2097823ae85adbd68c56.jpg",
    "followerDiff": "8.58w",
    "isCollect": null,
    "level": "6",
    "likeCount": "27.01w",
    "maxSex": {
      "count": "0",
      "key": "男",
      "rate": "77.54%"
    },
    "mid": "1119253352",
    "name": "顾我电影",
    "newrankIndex": "981.9",
    "officialTitle": "bilibili 知名影视UP主",
    "officialType": "0",
    "opusCount": "1",
    "playCount": "677.64w",
    "profession": null,
    "rankPosition": 6,
    "sex": "男",
    "type": "影视",
    "videoReviewCount": "4150"
  },
  {
    "coinCount": "4.66w",
    "face": "http://i2.hdslb.com/bfs/face/6b2ade215ea603b495648875c925172a863d16d4.jpg",
    "followerDiff": "9048",
    "isCollect": null,
    "level": "6",
    "likeCount": "5.55w",
    "maxSex": {
      "count": "0",
      "key": "男",
      "rate": "72.95%"
    },
    "mid": "17819768",
    "name": "电影最TOP",
    "newrankIndex": "980.7",
    "officialTitle": "bilibili 2022百大UP主、知名影视UP主",
    "officialType": "0",
    "opusCount": "1",
    "playCount": "68.30w",
    "profession": null,
    "rankPosition": 7,
    "sex": "男",
    "type": "影视",
    "videoReviewCount": "9684"
  },
  {
    "coinCount": "2.34w",
    "face": "https://i2.hdslb.com/bfs/face/6ccceba6ec8fe60d700f9f7c2910c08d70b03fe3.jpg",
    "followerDiff": "5.09w",
    "isCollect": null,
    "level": "6",
    "likeCount": "31.32w",
    "maxSex": {
      "count": "1322",
      "key": "男",
      "rate": "21.95%"
    },
    "mid": "604710494",
    "name": "长片短解",
    "newrankIndex": "968.7",
    "officialTitle": "长片短解官方账号",
    "officialType": "0",
    "opusCount": "4",
    "playCount": "637.96w",
    "profession": null,
    "rankPosition": 8,
    "sex": "男",
    "type": "影视",
    "videoReviewCount": "9296"
  },
  {
    "coinCount": "1.18w",
    "face": "https://i2.hdslb.com/bfs/face/a650215d10dc6e7d1b04663006fabe4ca731df24.jpg",
    "followerDiff": "8913",
    "isCollect": null,
    "level": "6",
    "likeCount": "23.28w",
    "maxSex": {
      "count": "0",
      "key": "男",
      "rate": "80.02%"
    },
    "mid": "8465957",
    "name": "乌鸦预告片",
    "newrankIndex": "951.1",
    "officialTitle": "bilibili 知名影视UP主",
    "officialType": "0",
    "opusCount": "37",
    "playCount": "475.25w",
    "profession": null,
    "rankPosition": 9,
    "sex": "保密",
    "type": "影视",
    "videoReviewCount": "1.79w"
  },
  {
    "coinCount": "1.86w",
    "face": "http://i1.hdslb.com/bfs/face/aad3b1bb735d2bd4066805f2a84892644fad8e2a.jpg",
    "followerDiff": "1.52w",
    "isCollect": null,
    "level": "6",
    "likeCount": "24.72w",
    "maxSex": {
      "count": "0",
      "key": "男",
      "rate": "88.70%"
    },
    "mid": "19286458",
    "name": "陈翔六点半",
    "newrankIndex": "950.6",
    "officialTitle": "bilibili 知名UP主",
    "officialType": "0",
    "opusCount": "5",
    "playCount": "440.37w",
    "profession": null,
    "rankPosition": 10,
    "sex": "男",
    "type": "影视",
    "videoReviewCount": "6531"
  },
  {
    "coinCount": "2.23w",
    "face": "https://i2.hdslb.com/bfs/face/37954c84facfe0751a14e3d93cf5f248f729cacc.jpg",
    "followerDiff": "2.47w",
    "isCollect": null,
    "level": "6",
    "likeCount": "18.83w",
    "maxSex": {
      "count": "0",
      "key": "男",
      "rate": "93.67%"
    },
    "mid": "388477943",
    "name": "薪儿姐师尊",
    "newrankIndex": "950.4",
    "officialTitle": "薪儿姐师尊官方账号，短剧UP主",
    "officialType": "0",
    "opusCount": "1",
    "playCount": "150.76w",
    "profession": null,
    "rankPosition": 11,
    "sex": "保密",
    "type": "影视",
    "videoReviewCount": "4027"
  },
  {
    "coinCount": "1.58w",
    "face": "https://i1.hdslb.com/bfs/face/3bae6a8f39f59b3212685b60dfef14b4fa4725d1.jpg",
    "followerDiff": "2.12w",
    "isCollect": null,
    "level": "6",
    "likeCount": "8.46w",
    "maxSex": {
      "count": "0",
      "key": "男",
      "rate": "69.52%"
    },
    "mid": "323588182",
    "name": "毒舌电影",
    "newrankIndex": "944.9",
    "officialTitle": "bilibili 知名影视UP主",
    "officialType": "0",
    "opusCount": "2",
    "playCount": "170.00w",
    "profession": null,
    "rankPosition": 12,
    "sex": "保密",
    "type": "影视",
    "videoReviewCount": "9947"
  },
  {
    "coinCount": "1.22w",
    "face": "https://i1.hdslb.com/bfs/face/b2e1ed03c4b1996088ac084ee0a96d2d4d816a43.jpg",
    "followerDiff": "2.16w",
    "isCollect": null,
    "level": "6",
    "likeCount": "16.40w",
    "maxSex": {
      "count": "0",
      "key": "男",
      "rate": "62.65%"
    },
    "mid": "525382468",
    "name": "人间放映厅",
    "newrankIndex": "942.8",
    "officialTitle": "",
    "officialType": "-1",
    "opusCount": "6",
    "playCount": "293.98w",
    "profession": null,
    "rankPosition": 13,
    "sex": "保密",
    "type": "影视",
    "videoReviewCount": "1.12w"
  },
  {
    "coinCount": "1.52w",
    "face": "https://i0.hdslb.com/bfs/face/225b8ef554ed65ac3c5e137262a252ef4b411e64.jpg",
    "followerDiff": "1.45w",
    "isCollect": null,
    "level": "6",
    "likeCount": "3.28w",
    "maxSex": {
      "count": "0",
      "key": "男",
      "rate": "72.52%"
    },
    "mid": "386869863",
    "name": "培根悖论唠唠嗑",
    "newrankIndex": "941.5",
    "officialTitle": "bilibili 2022百大UP主、知名影视UP主",
    "officialType": "0",
    "opusCount": "1",
    "playCount": "55.27w",
    "profession": null,
    "rankPosition": 14,
    "sex": "保密",
    "type": "影视",
    "videoReviewCount": "5094"
  },
  {
    "coinCount": "1.57w",
    "face": "https://i0.hdslb.com/bfs/face/a2131d38a2ea73f16ff25e61dbeb40377233f552.jpg",
    "followerDiff": "1.73w",
    "isCollect": null,
    "level": "6",
    "likeCount": "9.56w",
    "maxSex": {
      "count": "0",
      "key": "男",
      "rate": "67.93%"
    },
    "mid": "348989367",
    "name": "沫子瞪片",
    "newrankIndex": "938.9",
    "officialTitle": "bilibili 知名影视UP主",
    "officialType": "0",
    "opusCount": "3",
    "playCount": "100.34w",
    "profession": null,
    "rankPosition": 15,
    "sex": "男",
    "type": "影视",
    "videoReviewCount": "5266"
  },
  {
    "coinCount": "1.74w",
    "face": "https://i0.hdslb.com/bfs/face/0e77e2234de7fc1566461c8f661bd4c55cd5e9cb.jpg",
    "followerDiff": "2.28w",
    "isCollect": null,
    "level": "6",
    "likeCount": "3.42w",
    "maxSex": {
      "count": "0",
      "key": "男",
      "rate": "71.99%"
    },
    "mid": "17588331",
    "name": "青蛙刀圣_1993",
    "newrankIndex": "937.8",
    "officialTitle": "bilibili 知名影视UP主",
    "officialType": "0",
    "opusCount": "1",
    "playCount": "55.48w",
    "profession": null,
    "rankPosition": 16,
    "sex": "男",
    "type": "影视",
    "videoReviewCount": "2662"
  },
  {
    "coinCount": "8894",
    "face": "https://i2.hdslb.com/bfs/face/5cd3053f352bc597bac3d11b824e548108423cb2.jpg",
    "followerDiff": "5476",
    "isCollect": null,
    "level": "6",
    "likeCount": "10.96w",
    "maxSex": {
      "count": "0",
      "key": "女",
      "rate": "54.92%"
    },
    "mid": "203337614",
    "name": "开心嘴炮",
    "newrankIndex": "935.2",
    "officialTitle": "bilibili 知名娱乐UP主",
    "officialType": "0",
    "opusCount": "3",
    "playCount": "269.03w",
    "profession": null,
    "rankPosition": 17,
    "sex": "保密",
    "type": "影视",
    "videoReviewCount": "1.53w"
  },
  {
    "coinCount": "2.70w",
    "face": "https://i1.hdslb.com/bfs/face/7a8b609b7ca149bfcf89de50f804e3c8c3aa1ef9.jpg",
    "followerDiff": "1.24w",
    "isCollect": null,
    "level": "6",
    "likeCount": "5.81w",
    "maxSex": {
      "count": "0",
      "key": "男",
      "rate": "72.07%"
    },
    "mid": "11482657",
    "name": "东倾电影",
    "newrankIndex": "931.6",
    "officialTitle": "bilibili 知名影视UP主",
    "officialType": "0",
    "opusCount": "2",
    "playCount": "86.02w",
    "profession": null,
    "rankPosition": 18,
    "sex": "保密",
    "type": "影视",
    "videoReviewCount": "4075"
  },
  {
    "coinCount": "4.39w",
    "face": "https://i0.hdslb.com/bfs/face/5ad8dfbf8f2d23affcc4f8c8c12a8ad8f109bad0.jpg",
    "followerDiff": "5367",
    "isCollect": null,
    "level": "6",
    "likeCount": "6.18w",
    "maxSex": {
      "count": "0",
      "key": "男",
      "rate": "86.33%"
    },
    "mid": "8049684",
    "name": "绝命墨菲",
    "newrankIndex": "926.5",
    "officialTitle": "bilibili 知名影视UP主",
    "officialType": "0",
    "opusCount": "2",
    "playCount": "58.77w",
    "profession": null,
    "rankPosition": 19,
    "sex": "保密",
    "type": "影视",
    "videoReviewCount": "5064"
  },
  {
    "coinCount": "8741",
    "face": "http://i2.hdslb.com/bfs/face/812153babfd30220e578529226017267a8c0cb48.jpg",
    "followerDiff": "7147",
    "isCollect": null,
    "level": "6",
    "likeCount": "9.80w",
    "maxSex": {
      "count": "0",
      "key": "女",
      "rate": "72.25%"
    },
    "mid": "6739643",
    "name": "话很多的小姐姐们",
    "newrankIndex": "923.2",
    "officialTitle": "bilibili 知名影视UP主",
    "officialType": "0",
    "opusCount": "3",
    "playCount": "194.05w",
    "profession": null,
    "rankPosition": 20,
    "sex": "女",
    "type": "影视",
    "videoReviewCount": "1.73w"
  },
  {
    "coinCount": "8136",
    "face": "https://i2.hdslb.com/bfs/face/7e1eadcd221116fe8ff81ad5d263580de7155ef3.jpg",
    "followerDiff": "1.16w",
    "isCollect": null,
    "level": "6",
    "likeCount": "16.08w",
    "maxSex": {
      "count": "0",
      "key": "男",
      "rate": "73.78%"
    },
    "mid": "7428971",
    "name": "尽整没用的",
    "newrankIndex": "921.2",
    "officialTitle": "bilibili 知名影视UP主",
    "officialType": "0",
    "opusCount": "8",
    "playCount": "220.19w",
    "profession": null,
    "rankPosition": 21,
    "sex": "男",
    "type": "影视",
    "videoReviewCount": "4149"
  },
  {
    "coinCount": "1.83w",
    "face": "https://i1.hdslb.com/bfs/face/5622859595f53194b6209db32a9ef2674522ead1.jpg",
    "followerDiff": "1.53w",
    "isCollect": null,
    "level": "6",
    "likeCount": "17.53w",
    "maxSex": {
      "count": "0",
      "key": "男",
      "rate": "65.46%"
    },
    "mid": "385564720",
    "name": "马走日出",
    "newrankIndex": "913.3",
    "officialTitle": "",
    "officialType": "-1",
    "opusCount": "3",
    "playCount": "87.49w",
    "profession": null,
    "rankPosition": 22,
    "sex": "男",
    "type": "影视",
    "videoReviewCount": "1692"
  },
  {
    "coinCount": "6812",
    "face": "https://i1.hdslb.com/bfs/face/8065fae28268118303d227fd9bbba119c5a5d5be.jpg",
    "followerDiff": "2.39w",
    "isCollect": null,
    "level": "6",
    "likeCount": "5.42w",
    "maxSex": {
      "count": "0",
      "key": "男",
      "rate": "60.18%"
    },
    "mid": "452600545",
    "name": "悬疑MOVIE",
    "newrankIndex": "911.2",
    "officialTitle": "bilibili 知名影视UP主",
    "officialType": "0",
    "opusCount": "3",
    "playCount": "175.20w",
    "profession": null,
    "rankPosition": 23,
    "sex": "保密",
    "type": "影视",
    "videoReviewCount": "4408"
  },
  {
    "coinCount": "9304",
    "face": "https://i2.hdslb.com/bfs/face/79c1cf49166f6354d8814e93a4c8e1b55cfc03f2.jpg",
    "followerDiff": "1.49w",
    "isCollect": null,
    "level": "6",
    "likeCount": "2.75w",
    "maxSex": {
      "count": "0",
      "key": "男",
      "rate": "82.99%"
    },
    "mid": "8096990",
    "name": "啊粥粥啊粥",
    "newrankIndex": "907.3",
    "officialTitle": "bilibili 2021新人奖UP主、知名UP主",
    "officialType": "0",
    "opusCount": "1",
    "playCount": "49.55w",
    "profession": null,
    "rankPosition": 24,
    "sex": "男",
    "type": "影视",
    "videoReviewCount": "4486"
  },
  {
    "coinCount": "9355",
    "face": "http://i2.hdslb.com/bfs/face/f5086931232b524555a67098b027cfe1e0b79b64.jpg",
    "followerDiff": "3.70w",
    "isCollect": null,
    "level": "6",
    "likeCount": "3.02w",
    "maxSex": {
      "count": "0",
      "key": "男",
      "rate": "84.92%"
    },
    "mid": "407275913",
    "name": "假装讲电影",
    "newrankIndex": "906.3",
    "officialTitle": "bilibili 知名影视UP主",
    "officialType": "0",
    "opusCount": "1",
    "playCount": "37.23w",
    "profession": null,
    "rankPosition": 25,
    "sex": "男",
    "type": "影视",
    "videoReviewCount": "2628"
  },
  {
    "coinCount": "5085",
    "face": "https://i1.hdslb.com/bfs/face/b830989d9b8af6001da511a8a95b0ea806c11b60.jpg",
    "followerDiff": "4104",
    "isCollect": null,
    "level": "6",
    "likeCount": "5.60w",
    "maxSex": {
      "count": "0",
      "key": "女",
      "rate": "57.26%"
    },
    "mid": "29296192",
    "name": "虫哥说电影",
    "newrankIndex": "904.9",
    "officialTitle": "bilibili 知名影视UP主",
    "officialType": "0",
    "opusCount": "2",
    "playCount": "142.98w",
    "profession": null,
    "rankPosition": 26,
    "sex": "男",
    "type": "影视",
    "videoReviewCount": "1.14w"
  },
  {
    "coinCount": "9075",
    "face": "https://i0.hdslb.com/bfs/face/986bf531f3e50a6bf67d5844f9304fc310a153e3.jpg",
    "followerDiff": "1.06w",
    "isCollect": null,
    "level": "6",
    "likeCount": "3.28w",
    "maxSex": {
      "count": "0",
      "key": "男",
      "rate": "72.89%"
    },
    "mid": "390898500",
    "name": "一目十影",
    "newrankIndex": "904.6",
    "officialTitle": "bilibili 知名影视UP主",
    "officialType": "0",
    "opusCount": "1",
    "playCount": "63.54w",
    "profession": null,
    "rankPosition": 27,
    "sex": "男",
    "type": "影视",
    "videoReviewCount": "2722"
  },
  {
    "coinCount": "5780",
    "face": "https://i0.hdslb.com/bfs/face/8a1e617a0730cef6f13694d1e2c5a3a71e09b955.jpg",
    "followerDiff": "1.21w",
    "isCollect": null,
    "level": "6",
    "likeCount": "23.18w",
    "maxSex": {
      "count": "0",
      "key": "男",
      "rate": "83.53%"
    },
    "mid": "381339027",
    "name": "7块电影",
    "newrankIndex": "903.6",
    "officialTitle": "bilibili 知名影视UP主",
    "officialType": "0",
    "opusCount": "3",
    "playCount": "359.86w",
    "profession": null,
    "rankPosition": 28,
    "sex": "男",
    "type": "影视",
    "videoReviewCount": "9691"
  },
  {
    "coinCount": "1.20w",
    "face": "https://i1.hdslb.com/bfs/face/58772b63be427a2340ce780c766cad11f68c8380.jpg",
    "followerDiff": "8373",
    "isCollect": null,
    "level": "6",
    "likeCount": "4.73w",
    "maxSex": {
      "count": "0",
      "key": "男",
      "rate": "81.79%"
    },
    "mid": "21778075",
    "name": "_青红造了个白_",
    "newrankIndex": "902.2",
    "officialTitle": "青红造了个白官方账号，影视剪辑自媒体",
    "officialType": "0",
    "opusCount": "1",
    "playCount": "40.38w",
    "profession": null,
    "rankPosition": 29,
    "sex": "男",
    "type": "影视",
    "videoReviewCount": "2663"
  },
  {
    "coinCount": "3211",
    "face": "https://i2.hdslb.com/bfs/face/fabe17ef4b344336b872e3ded46a4a4b11140e7f.jpg",
    "followerDiff": "6887",
    "isCollect": null,
    "level": "6",
    "likeCount": "3.63w",
    "maxSex": {
      "count": "0",
      "key": "女",
      "rate": "70.59%"
    },
    "mid": "34189415",
    "name": "low君热剧",
    "newrankIndex": "896.8",
    "officialTitle": "bilibili 知名UP主",
    "officialType": "0",
    "opusCount": "1",
    "playCount": "64.53w",
    "profession": null,
    "rankPosition": 30,
    "sex": "男",
    "type": "影视",
    "videoReviewCount": "9074"
  },
  {
    "coinCount": "2.44w",
    "face": "http://i2.hdslb.com/bfs/face/08376a7e475c3c48d5f7b2781fe5d92c94bc0ea4.jpg",
    "followerDiff": "3332",
    "isCollect": null,
    "level": "6",
    "likeCount": "7.80w",
    "maxSex": {
      "count": "0",
      "key": "男",
      "rate": "91.64%"
    },
    "mid": "304815404",
    "name": "流心影者",
    "newrankIndex": "896.0",
    "officialTitle": "bilibili 知名影视UP主",
    "officialType": "0",
    "opusCount": "4",
    "playCount": "223.09w",
    "profession": null,
    "rankPosition": 31,
    "sex": "保密",
    "type": "影视",
    "videoReviewCount": "3969"
  },
  {
    "coinCount": "3891",
    "face": "https://i1.hdslb.com/bfs/face/78c27b565e56598877a70bed015974253b14eef7.jpg",
    "followerDiff": "9287",
    "isCollect": null,
    "level": "6",
    "likeCount": "6.56w",
    "maxSex": {
      "count": "0",
      "key": "男",
      "rate": "87.56%"
    },
    "mid": "206840230",
    "name": "科幻Fans布玛",
    "newrankIndex": "894.5",
    "officialTitle": "bilibili 知名UP主",
    "officialType": "0",
    "opusCount": "5",
    "playCount": "100.29w",
    "profession": null,
    "rankPosition": 32,
    "sex": "女",
    "type": "影视",
    "videoReviewCount": "4304"
  },
  {
    "coinCount": "9384",
    "face": "https://i2.hdslb.com/bfs/face/f67d68fb42cf550e624e5db4730388bb5c7eeb56.jpg",
    "followerDiff": "5450",
    "isCollect": null,
    "level": "6",
    "likeCount": "2.48w",
    "maxSex": {
      "count": "0",
      "key": "男",
      "rate": "74.08%"
    },
    "mid": "942755",
    "name": "迷影至下Filmlast",
    "newrankIndex": "893.4",
    "officialTitle": "bilibili 知名影视UP主",
    "officialType": "0",
    "opusCount": "4",
    "playCount": "76.66w",
    "profession": null,
    "rankPosition": 33,
    "sex": "男",
    "type": "影视",
    "videoReviewCount": "4014"
  },
  {
    "coinCount": "5160",
    "face": "https://i1.hdslb.com/bfs/face/eb00c45c2815df0667f66cec4581d0727a7c77df.jpg",
    "followerDiff": "5321",
    "isCollect": null,
    "level": "6",
    "likeCount": "4.91w",
    "maxSex": {
      "count": "0",
      "key": "男",
      "rate": "85.31%"
    },
    "mid": "395991094",
    "name": "电影迷小雅",
    "newrankIndex": "888.8",
    "officialTitle": "bilibili 知名影视UP主",
    "officialType": "0",
    "opusCount": "7",
    "playCount": "100.53w",
    "profession": null,
    "rankPosition": 34,
    "sex": "女",
    "type": "影视",
    "videoReviewCount": "4566"
  },
  {
    "coinCount": "2926",
    "face": "https://i1.hdslb.com/bfs/face/c8a1e0fcfc70d727010bd072dd539a7ee7d14d21.jpg",
    "followerDiff": "9903",
    "isCollect": null,
    "level": "6",
    "likeCount": "8.76w",
    "maxSex": {
      "count": "0",
      "key": "男",
      "rate": "80.13%"
    },
    "mid": "243566998",
    "name": "挖沟连彭沟长",
    "newrankIndex": "887.3",
    "officialTitle": "bilibili 知名影视UP主",
    "officialType": "0",
    "opusCount": "5",
    "playCount": "192.60w",
    "profession": null,
    "rankPosition": 35,
    "sex": "保密",
    "type": "影视",
    "videoReviewCount": "6904"
  },
  {
    "coinCount": "7780",
    "face": "https://i2.hdslb.com/bfs/face/981234c46a81361eedbdcdb48f156ddd08298622.jpg",
    "followerDiff": "6951",
    "isCollect": null,
    "level": "6",
    "likeCount": "1.97w",
    "maxSex": {
      "count": "0",
      "key": "男",
      "rate": "87.15%"
    },
    "mid": "25073738",
    "name": "科幻视界",
    "newrankIndex": "886.5",
    "officialTitle": "bilibili 知名影视UP主",
    "officialType": "0",
    "opusCount": "1",
    "playCount": "51.58w",
    "profession": null,
    "rankPosition": 36,
    "sex": "男",
    "type": "影视",
    "videoReviewCount": "1246"
  },
  {
    "coinCount": "1.68w",
    "face": "https://i1.hdslb.com/bfs/face/61e049c852528d6613d214ef4f0190e94254635f.jpg",
    "followerDiff": "851",
    "isCollect": null,
    "level": "6",
    "likeCount": "10.76w",
    "maxSex": {
      "count": "2230",
      "key": "男",
      "rate": "16.02%"
    },
    "mid": "43887712",
    "name": "爱睡觉的_Koala",
    "newrankIndex": "879.7",
    "officialTitle": "bilibili 知名影视UP主",
    "officialType": "0",
    "opusCount": "11",
    "playCount": "94.30w",
    "profession": null,
    "rankPosition": 37,
    "sex": "保密",
    "type": "影视",
    "videoReviewCount": "1602"
  },
  {
    "coinCount": "2411",
    "face": "https://i2.hdslb.com/bfs/face/654ed89c763ca1f003cc2d0145e1ec444cc7f0e8.jpg",
    "followerDiff": "6153",
    "isCollect": null,
    "level": "6",
    "likeCount": "2.42w",
    "maxSex": {
      "count": "0",
      "key": "男",
      "rate": "54.45%"
    },
    "mid": "27218150",
    "name": "刘哔电影",
    "newrankIndex": "874.0",
    "officialTitle": "bilibili 2018百大UP主、 知名影视UP主",
    "officialType": "0",
    "opusCount": "1",
    "playCount": "78.25w",
    "profession": null,
    "rankPosition": 38,
    "sex": "男",
    "type": "影视",
    "videoReviewCount": "2495"
  },
  {
    "coinCount": "3126",
    "face": "https://i1.hdslb.com/bfs/face/7e5226f99942d84341ca6a94b7cbb0ce3f183842.jpg",
    "followerDiff": "8315",
    "isCollect": null,
    "level": "6",
    "likeCount": "10.43w",
    "maxSex": {
      "count": "0",
      "key": "男",
      "rate": "86.00%"
    },
    "mid": "265004917",
    "name": "王小C_",
    "newrankIndex": "871.3",
    "officialTitle": "",
    "officialType": "-1",
    "opusCount": "10",
    "playCount": "349.25w",
    "profession": null,
    "rankPosition": 39,
    "sex": "男",
    "type": "影视",
    "videoReviewCount": "5683"
  },
  {
    "coinCount": "3.95w",
    "face": "https://i1.hdslb.com/bfs/face/b90967318b6883fd2d43c9b0ee1c7b3d2c5fc62b.jpg",
    "followerDiff": "5663",
    "isCollect": null,
    "level": "6",
    "likeCount": "17.72w",
    "maxSex": {
      "count": "821",
      "key": "男",
      "rate": "26.23%"
    },
    "mid": "441872026",
    "name": "健人鑫",
    "newrankIndex": "870.6",
    "officialTitle": "",
    "officialType": "-1",
    "opusCount": "6",
    "playCount": "179.73w",
    "profession": null,
    "rankPosition": 40,
    "sex": "男",
    "type": "影视",
    "videoReviewCount": "2987"
  },
  {
    "coinCount": "1.08w",
    "face": "https://i1.hdslb.com/bfs/face/e8d9323b2ae200e897a136188b3e197b06c94d34.jpg",
    "followerDiff": "6628",
    "isCollect": null,
    "level": "6",
    "likeCount": "9.22w",
    "maxSex": {
      "count": "2116",
      "key": "男",
      "rate": "24.64%"
    },
    "mid": "585957487",
    "name": "中核集团",
    "newrankIndex": "860.2",
    "officialTitle": "中核集团官方账号",
    "officialType": "1",
    "opusCount": "3",
    "playCount": "76.06w",
    "profession": null,
    "rankPosition": 41,
    "sex": "保密",
    "type": "影视",
    "videoReviewCount": "2183"
  },
  {
    "coinCount": "7038",
    "face": "https://i2.hdslb.com/bfs/face/fb563df080777b2eba77b93cd36d80168ea53d11.jpg",
    "followerDiff": "6802",
    "isCollect": null,
    "level": "6",
    "likeCount": "7.30w",
    "maxSex": {
      "count": "0",
      "key": "男",
      "rate": "95.31%"
    },
    "mid": "3461568046041659",
    "name": "搏bo搏",
    "newrankIndex": "859.9",
    "officialTitle": "bilibili 知名UP主",
    "officialType": "0",
    "opusCount": "3",
    "playCount": "74.88w",
    "profession": null,
    "rankPosition": 42,
    "sex": "男",
    "type": "影视",
    "videoReviewCount": "1306"
  },
  {
    "coinCount": "4481",
    "face": "https://i1.hdslb.com/bfs/face/9544915068f0cf3dbeb5e34d590cbaab2738dad8.jpg",
    "followerDiff": "1.20w",
    "isCollect": null,
    "level": "6",
    "likeCount": "16.53w",
    "maxSex": {
      "count": "1404",
      "key": "男",
      "rate": "32.50%"
    },
    "mid": "1805992672",
    "name": "创作失败",
    "newrankIndex": "856.1",
    "officialTitle": "",
    "officialType": "-1",
    "opusCount": "4",
    "playCount": "131.67w",
    "profession": null,
    "rankPosition": 43,
    "sex": "保密",
    "type": "影视",
    "videoReviewCount": "1739"
  },
  {
    "coinCount": "2062",
    "face": "https://i1.hdslb.com/bfs/face/f1df42e1b2d69b29176f142a0d40f856fb60f82d.jpg",
    "followerDiff": "5785",
    "isCollect": null,
    "level": "6",
    "likeCount": "14.01w",
    "maxSex": {
      "count": "0",
      "key": "男",
      "rate": "82.31%"
    },
    "mid": "145750219",
    "name": "电影冷知识",
    "newrankIndex": "855.8",
    "officialTitle": "电影冷知识官方账号、影视类视频自媒体",
    "officialType": "0",
    "opusCount": "3",
    "playCount": "153.42w",
    "profession": null,
    "rankPosition": 44,
    "sex": "男",
    "type": "影视",
    "videoReviewCount": "1929"
  },
  {
    "coinCount": "6286",
    "face": "https://i1.hdslb.com/bfs/face/d047999e5b1128a38da798f65ab44865622785db.jpg",
    "followerDiff": "1.08w",
    "isCollect": null,
    "level": "6",
    "likeCount": "4.60w",
    "maxSex": {
      "count": "0",
      "key": "女",
      "rate": "83.06%"
    },
    "mid": "1570971364",
    "name": "追娘娘特别肝",
    "newrankIndex": "854.5",
    "officialTitle": "bilibili 知名UP主",
    "officialType": "0",
    "opusCount": "3",
    "playCount": "105.12w",
    "profession": null,
    "rankPosition": 45,
    "sex": "保密",
    "type": "影视",
    "videoReviewCount": "2483"
  },
  {
    "coinCount": "1087",
    "face": "https://i2.hdslb.com/bfs/face/7a3ccfa2d021bc1212ffdd5ea637d098a1475d9f.jpg",
    "followerDiff": "3.28w",
    "isCollect": null,
    "level": "6",
    "likeCount": "4.10w",
    "maxSex": {
      "count": "0",
      "key": "男",
      "rate": "84.71%"
    },
    "mid": "73528331",
    "name": "摩斯神探",
    "newrankIndex": "853.2",
    "officialTitle": "摩斯神探官方账号，知名影视UP主",
    "officialType": "0",
    "opusCount": "1",
    "playCount": "53.58w",
    "profession": null,
    "rankPosition": 46,
    "sex": "男",
    "type": "影视",
    "videoReviewCount": "1443"
  },
  {
    "coinCount": "11.67w",
    "face": "https://i2.hdslb.com/bfs/face/0e225586344f2eb0788988b88157c0b1405858ae.jpg",
    "followerDiff": "1639",
    "isCollect": null,
    "level": "6",
    "likeCount": "22.78w",
    "maxSex": {
      "count": "572",
      "key": "男",
      "rate": "16.19%"
    },
    "mid": "105238655",
    "name": "头号宇航员",
    "newrankIndex": "853.1",
    "officialTitle": "",
    "officialType": "-1",
    "opusCount": "3",
    "playCount": "236.00w",
    "profession": null,
    "rankPosition": 47,
    "sex": "女",
    "type": "影视",
    "videoReviewCount": "4685"
  },
  {
    "coinCount": "2256",
    "face": "https://i2.hdslb.com/bfs/face/7d7631c0cc3201afd2326eca2bec4b7c12786d87.jpg",
    "followerDiff": "2.18w",
    "isCollect": null,
    "level": "6",
    "likeCount": "2.96w",
    "maxSex": {
      "count": "0",
      "key": "男",
      "rate": "84.01%"
    },
    "mid": "1457639978",
    "name": "正说清代十二朝",
    "newrankIndex": "849.0",
    "officialTitle": "bilibili 知名影视UP主",
    "officialType": "0",
    "opusCount": "4",
    "playCount": "74.90w",
    "profession": null,
    "rankPosition": 48,
    "sex": "男",
    "type": "影视",
    "videoReviewCount": "1716"
  },
  {
    "coinCount": "3993",
    "face": "https://i0.hdslb.com/bfs/face/37e100b64ed8192726679b702a4836d8424b17aa.jpg",
    "followerDiff": "2433",
    "isCollect": null,
    "level": "6",
    "likeCount": "6.30w",
    "maxSex": {
      "count": "0",
      "key": "男",
      "rate": "71.08%"
    },
    "mid": "240769971",
    "name": "神烦XP",
    "newrankIndex": "847.9",
    "officialTitle": "bilibili 知名UP主",
    "officialType": "0",
    "opusCount": "6",
    "playCount": "127.91w",
    "profession": null,
    "rankPosition": 49,
    "sex": "保密",
    "type": "影视",
    "videoReviewCount": "2753"
  },
  {
    "coinCount": "7693",
    "face": "https://i1.hdslb.com/bfs/face/bfe2ba392dba0a8e1073faf295196524850b6266.jpg",
    "followerDiff": "1.20w",
    "isCollect": null,
    "level": "6",
    "likeCount": "4.44w",
    "maxSex": {
      "count": "710",
      "key": "女",
      "rate": "23.82%"
    },
    "mid": "6468436",
    "name": "发疯达人陈六斤",
    "newrankIndex": "847.7",
    "officialTitle": "",
    "officialType": "-1",
    "opusCount": "1",
    "playCount": "97.87w",
    "profession": null,
    "rankPosition": 50,
    "sex": "保密",
    "type": "影视",
    "videoReviewCount": "4533"
  },
  {
    "coinCount": "4215",
    "face": "https://i2.hdslb.com/bfs/face/323e5987c19c580937f5add9212acc5075a97d06.jpg",
    "followerDiff": "2.14w",
    "isCollect": null,
    "level": "6",
    "likeCount": "23.88w",
    "maxSex": {
      "count": "777",
      "key": "男",
      "rate": "22.18%"
    },
    "mid": "102805877",
    "name": "西维西师傅",
    "newrankIndex": "847.3",
    "officialTitle": "bilibili 知名搞笑UP主",
    "officialType": "0",
    "opusCount": "2",
    "playCount": "201.88w",
    "profession": null,
    "rankPosition": 51,
    "sex": "保密",
    "type": "影视",
    "videoReviewCount": "432"
  },
  {
    "coinCount": "2010",
    "face": "https://i1.hdslb.com/bfs/face/24a3e01e14892b458fafc3d8102d2a99cc2ea90c.jpg",
    "followerDiff": "4172",
    "isCollect": null,
    "level": "6",
    "likeCount": "5.30w",
    "maxSex": {
      "count": "0",
      "key": "男",
      "rate": "84.70%"
    },
    "mid": "687664429",
    "name": "猛虎电影",
    "newrankIndex": "847.2",
    "officialTitle": "bilibili 知名影视UP主",
    "officialType": "0",
    "opusCount": "2",
    "playCount": "221.97w",
    "profession": null,
    "rankPosition": 52,
    "sex": "男",
    "type": "影视",
    "videoReviewCount": "1866"
  },
  {
    "coinCount": "1.62w",
    "face": "https://i0.hdslb.com/bfs/face/26db33202556c8d3b0b303a530da3848f7788bb0.jpg",
    "followerDiff": "2707",
    "isCollect": null,
    "level": "6",
    "likeCount": "5.83w",
    "maxSex": {
      "count": "0",
      "key": "女",
      "rate": "64.49%"
    },
    "mid": "23113971",
    "name": "菊蛤xx",
    "newrankIndex": "845.9",
    "officialTitle": "",
    "officialType": "-1",
    "opusCount": "3",
    "playCount": "81.02w",
    "profession": null,
    "rankPosition": 53,
    "sex": "保密",
    "type": "影视",
    "videoReviewCount": "1321"
  },
  {
    "coinCount": "9598",
    "face": "https://i2.hdslb.com/bfs/face/f864febf169ff495e6895f3b73ccb6a273fb555d.jpg",
    "followerDiff": "5075",
    "isCollect": null,
    "level": "6",
    "likeCount": "2.48w",
    "maxSex": {
      "count": "0",
      "key": "女",
      "rate": "80.87%"
    },
    "mid": "96967343",
    "name": "大喜唠嗑家",
    "newrankIndex": "844.9",
    "officialTitle": "bilibili 知名影视UP主",
    "officialType": "0",
    "opusCount": "1",
    "playCount": "24.05w",
    "profession": null,
    "rankPosition": 54,
    "sex": "保密",
    "type": "影视",
    "videoReviewCount": "1085"
  },
  {
    "coinCount": "7794",
    "face": "https://i0.hdslb.com/bfs/face/e8457df1bce89ff11a92ec3ff40b4b8022aa2c28.jpg",
    "followerDiff": "981",
    "isCollect": null,
    "level": "6",
    "likeCount": "9.72w",
    "maxSex": {
      "count": "832",
      "key": "女",
      "rate": "20.85%"
    },
    "mid": "514297335",
    "name": "EndingKJY",
    "newrankIndex": "843.3",
    "officialTitle": "",
    "officialType": "-1",
    "opusCount": "28",
    "playCount": "379.08w",
    "profession": null,
    "rankPosition": 55,
    "sex": "保密",
    "type": "影视",
    "videoReviewCount": "7728"
  },
  {
    "coinCount": "8962",
    "face": "https://i0.hdslb.com/bfs/face/d721f1f3388b039e491c94a0abfaeab122429696.jpg",
    "followerDiff": "5733",
    "isCollect": null,
    "level": "6",
    "likeCount": "1.22w",
    "maxSex": {
      "count": "0",
      "key": "男",
      "rate": "88.51%"
    },
    "mid": "7957044",
    "name": "我是十四哦丶",
    "newrankIndex": "842.6",
    "officialTitle": "bilibili 知名影视UP主",
    "officialType": "0",
    "opusCount": "1",
    "playCount": "20.12w",
    "profession": null,
    "rankPosition": 56,
    "sex": "保密",
    "type": "影视",
    "videoReviewCount": "3230"
  },
  {
    "coinCount": "6932",
    "face": "https://i0.hdslb.com/bfs/face/a666e4781e2f2906fe8dbc4cff6d8bcf80cf11d7.jpg",
    "followerDiff": "5534",
    "isCollect": null,
    "level": "6",
    "likeCount": "6.24w",
    "maxSex": {
      "count": "0",
      "key": "男",
      "rate": "94.93%"
    },
    "mid": "1342657662",
    "name": "东乐剧院",
    "newrankIndex": "841.5",
    "officialTitle": "bilibili 知名影视UP主",
    "officialType": "0",
    "opusCount": "3",
    "playCount": "91.53w",
    "profession": null,
    "rankPosition": 57,
    "sex": "男",
    "type": "影视",
    "videoReviewCount": "2692"
  },
  {
    "coinCount": "3830",
    "face": "https://i2.hdslb.com/bfs/face/bc36fb870770a46ceb56852ccb516d4af064dc9b.jpg",
    "followerDiff": "7395",
    "isCollect": null,
    "level": "6",
    "likeCount": "6.42w",
    "maxSex": {
      "count": "1029",
      "key": "女",
      "rate": "20.94%"
    },
    "mid": "677580188",
    "name": "尚恬菲",
    "newrankIndex": "840.9",
    "officialTitle": "",
    "officialType": "-1",
    "opusCount": "7",
    "playCount": "47.27w",
    "profession": null,
    "rankPosition": 58,
    "sex": "保密",
    "type": "影视",
    "videoReviewCount": "1126"
  },
  {
    "coinCount": "4171",
    "face": "http://i1.hdslb.com/bfs/face/bb4180a5200d49de94aa1d4f986f4011d41ff52b.jpg",
    "followerDiff": "7575",
    "isCollect": null,
    "level": "6",
    "likeCount": "14.27w",
    "maxSex": {
      "count": "2796",
      "key": "男",
      "rate": "22.80%"
    },
    "mid": "580062043",
    "name": "刘老根大舞台官方账号",
    "newrankIndex": "840.8",
    "officialTitle": "辽宁民间艺术团官方账号",
    "officialType": "1",
    "opusCount": "14",
    "playCount": "279.41w",
    "profession": null,
    "rankPosition": 59,
    "sex": "女",
    "type": "影视",
    "videoReviewCount": "1149"
  },
  {
    "coinCount": "6664",
    "face": "https://i2.hdslb.com/bfs/face/b70278c1e89cab4cc5c8b00803f7ecce11b2c1f1.jpg",
    "followerDiff": "2872",
    "isCollect": null,
    "level": "6",
    "likeCount": "1.49w",
    "maxSex": {
      "count": "0",
      "key": "男",
      "rate": "81.87%"
    },
    "mid": "253350665",
    "name": "大聪看电影",
    "newrankIndex": "840.1",
    "officialTitle": "bilibili 知名影视UP主",
    "officialType": "0",
    "opusCount": "2",
    "playCount": "17.80w",
    "profession": null,
    "rankPosition": 60,
    "sex": "男",
    "type": "影视",
    "videoReviewCount": "777"
  },
  {
    "coinCount": "2655",
    "face": "https://i2.hdslb.com/bfs/face/a8cc916b7db3d51ab637d98f2be234c447d17993.jpg",
    "followerDiff": "6574",
    "isCollect": null,
    "level": "6",
    "likeCount": "1.79w",
    "maxSex": {
      "count": "0",
      "key": "男",
      "rate": "80.74%"
    },
    "mid": "40545158",
    "name": "散装官人",
    "newrankIndex": "839.6",
    "officialTitle": "bilibili 知名影视UP主",
    "officialType": "0",
    "opusCount": "1",
    "playCount": "55.14w",
    "profession": null,
    "rankPosition": 61,
    "sex": "男",
    "type": "影视",
    "videoReviewCount": "1710"
  },
  {
    "coinCount": "1918",
    "face": "https://i1.hdslb.com/bfs/face/5c73b62ba27830496c125f581b09214bab0bf730.jpg",
    "followerDiff": "7619",
    "isCollect": null,
    "level": "6",
    "likeCount": "4.43w",
    "maxSex": {
      "count": "0",
      "key": "男",
      "rate": "94.35%"
    },
    "mid": "1767848350",
    "name": "宝哥哥说电影",
    "newrankIndex": "837.8",
    "officialTitle": "bilibili 知名影视UP主",
    "officialType": "0",
    "opusCount": "2",
    "playCount": "94.42w",
    "profession": null,
    "rankPosition": 62,
    "sex": "男",
    "type": "影视",
    "videoReviewCount": "2410"
  },
  {
    "coinCount": "2102",
    "face": "https://i0.hdslb.com/bfs/face/1a4e6f17db62bc78f16831f9d68ae5abe3d02147.jpg",
    "followerDiff": "1.17w",
    "isCollect": null,
    "level": "6",
    "likeCount": "2.06w",
    "maxSex": {
      "count": "525",
      "key": "男",
      "rate": "19.84%"
    },
    "mid": "392983644",
    "name": "浮生说剧",
    "newrankIndex": "835.9",
    "officialTitle": "",
    "officialType": "-1",
    "opusCount": "1",
    "playCount": "96.75w",
    "profession": null,
    "rankPosition": 63,
    "sex": "保密",
    "type": "影视",
    "videoReviewCount": "3388"
  },
  {
    "coinCount": "1323",
    "face": "https://i2.hdslb.com/bfs/face/08536b6ddd551778638bdd0a336f0a262412a00b.jpg",
    "followerDiff": "6746",
    "isCollect": null,
    "level": "6",
    "likeCount": "2.73w",
    "maxSex": {
      "count": "0",
      "key": "男",
      "rate": "84.11%"
    },
    "mid": "284864219",
    "name": "恐怖地带来恐怖",
    "newrankIndex": "835.5",
    "officialTitle": "bilibili 知名影视UP主",
    "officialType": "0",
    "opusCount": "2",
    "playCount": "58.35w",
    "profession": null,
    "rankPosition": 64,
    "sex": "男",
    "type": "影视",
    "videoReviewCount": "1946"
  },
  {
    "coinCount": "2319",
    "face": "https://i1.hdslb.com/bfs/face/f8fdd8594c2dc1536307009420c87f336677427a.jpg",
    "followerDiff": "2900",
    "isCollect": null,
    "level": "6",
    "likeCount": "10.89w",
    "maxSex": {
      "count": "0",
      "key": "男",
      "rate": "83.79%"
    },
    "mid": "403881577",
    "name": "诸葛皮皮9527",
    "newrankIndex": "833.3",
    "officialTitle": "bilibili 知名UP主",
    "officialType": "0",
    "opusCount": "3",
    "playCount": "79.73w",
    "profession": null,
    "rankPosition": 65,
    "sex": "保密",
    "type": "影视",
    "videoReviewCount": "1101"
  },
  {
    "coinCount": "6988",
    "face": "https://i0.hdslb.com/bfs/face/f84c2144fde8d7e629db054f7f9d6bfda6d004f8.jpg",
    "followerDiff": "1939",
    "isCollect": null,
    "level": "6",
    "likeCount": "1.15w",
    "maxSex": {
      "count": "0",
      "key": "男",
      "rate": "84.34%"
    },
    "mid": "10334523",
    "name": "史蒂芬周大反派",
    "newrankIndex": "831.9",
    "officialTitle": "bilibili 知名UP主",
    "officialType": "0",
    "opusCount": "1",
    "playCount": "13.80w",
    "profession": null,
    "rankPosition": 66,
    "sex": "男",
    "type": "影视",
    "videoReviewCount": "1676"
  },
  {
    "coinCount": "840",
    "face": "https://i2.hdslb.com/bfs/face/80f33842c62770b4520950fb3f42f9c73b488106.jpg",
    "followerDiff": "2980",
    "isCollect": null,
    "level": "6",
    "likeCount": "5.74w",
    "maxSex": {
      "count": "0",
      "key": "男",
      "rate": "86.97%"
    },
    "mid": "1569685991",
    "name": "船长电影解说",
    "newrankIndex": "831.5",
    "officialTitle": "bilibili 知名影视UP主",
    "officialType": "0",
    "opusCount": "9",
    "playCount": "205.63w",
    "profession": null,
    "rankPosition": 67,
    "sex": "男",
    "type": "影视",
    "videoReviewCount": "1741"
  },
  {
    "coinCount": "7114",
    "face": "https://i2.hdslb.com/bfs/face/b08364d2f7ebcf48dc5425654ebcc91054f01493.jpg",
    "followerDiff": "4339",
    "isCollect": null,
    "level": "6",
    "likeCount": "3.56w",
    "maxSex": {
      "count": "1477",
      "key": "男",
      "rate": "20.46%"
    },
    "mid": "286398266",
    "name": "老鸽0LDGE",
    "newrankIndex": "828.7",
    "officialTitle": "bilibili 知名UP主",
    "officialType": "0",
    "opusCount": "2",
    "playCount": "56.60w",
    "profession": null,
    "rankPosition": 68,
    "sex": "男",
    "type": "影视",
    "videoReviewCount": "2426"
  },
  {
    "coinCount": "3174",
    "face": "https://i1.hdslb.com/bfs/face/5ca0551ef8e575c1f164fc75144fd56ad36c1587.jpg",
    "followerDiff": "2206",
    "isCollect": null,
    "level": "6",
    "likeCount": "2.32w",
    "maxSex": {
      "count": "784",
      "key": "男",
      "rate": "19.59%"
    },
    "mid": "2020765549",
    "name": "大酱电影",
    "newrankIndex": "827.9",
    "officialTitle": "",
    "officialType": "-1",
    "opusCount": "2",
    "playCount": "104.08w",
    "profession": null,
    "rankPosition": 69,
    "sex": "男",
    "type": "影视",
    "videoReviewCount": "3457"
  },
  {
    "coinCount": "5863",
    "face": "https://i2.hdslb.com/bfs/face/44216c558762ea552c69fd857fe4d3a59a6e21e4.jpg",
    "followerDiff": "2953",
    "isCollect": null,
    "level": "5",
    "likeCount": "11.78w",
    "maxSex": {
      "count": "504",
      "key": "男",
      "rate": "17.18%"
    },
    "mid": "1402099574",
    "name": "我的史珍香",
    "newrankIndex": "827.4",
    "officialTitle": "",
    "officialType": "-1",
    "opusCount": "1",
    "playCount": "139.20w",
    "profession": null,
    "rankPosition": 70,
    "sex": "女",
    "type": "影视",
    "videoReviewCount": "1857"
  },
  {
    "coinCount": "1137",
    "face": "https://i1.hdslb.com/bfs/face/f5ea8b6ee8ef21f16f42a2c25410d27f2d7e28c0.jpg",
    "followerDiff": "2.15w",
    "isCollect": null,
    "level": "5",
    "likeCount": "37.86w",
    "maxSex": {
      "count": "77",
      "key": "男",
      "rate": "18.20%"
    },
    "mid": "3493295837677744",
    "name": "一芳在干嘛",
    "newrankIndex": "827.1",
    "officialTitle": "",
    "officialType": "-1",
    "opusCount": "5",
    "playCount": "405.12w",
    "profession": null,
    "rankPosition": 71,
    "sex": "保密",
    "type": "影视",
    "videoReviewCount": "339"
  },
  {
    "coinCount": "6474",
    "face": "https://i1.hdslb.com/bfs/face/315bf2cc895c3f07031d4419e1bfdb3fbb4aa7db.jpg",
    "followerDiff": "4694",
    "isCollect": null,
    "level": "6",
    "likeCount": "3.64w",
    "maxSex": {
      "count": "314",
      "key": "男",
      "rate": "14.36%"
    },
    "mid": "2050346308",
    "name": "茄子姐解说",
    "newrankIndex": "824.4",
    "officialTitle": "",
    "officialType": "-1",
    "opusCount": "8",
    "playCount": "83.09w",
    "profession": null,
    "rankPosition": 72,
    "sex": "保密",
    "type": "影视",
    "videoReviewCount": "1382"
  },
  {
    "coinCount": "3546",
    "face": "https://i1.hdslb.com/bfs/face/4f93e01a93844f89897a8b9a16d8c554acd4a121.jpg",
    "followerDiff": "1947",
    "isCollect": null,
    "level": "6",
    "likeCount": "1.31w",
    "maxSex": {
      "count": "0",
      "key": "男",
      "rate": "69.10%"
    },
    "mid": "149558293",
    "name": "越哥说电影",
    "newrankIndex": "823.0",
    "officialTitle": "bilibili 知名影视UP主",
    "officialType": "0",
    "opusCount": "3",
    "playCount": "27.69w",
    "profession": null,
    "rankPosition": 73,
    "sex": "保密",
    "type": "影视",
    "videoReviewCount": "602"
  },
  {
    "coinCount": "3143",
    "face": "https://i1.hdslb.com/bfs/face/3036c8911512860b33eddf4118640a7aefab7edb.jpg",
    "followerDiff": "2777",
    "isCollect": null,
    "level": "6",
    "likeCount": "2.46w",
    "maxSex": {
      "count": "123",
      "key": "男",
      "rate": "13.95%"
    },
    "mid": "3493135384578427",
    "name": "小王剧场",
    "newrankIndex": "823.0",
    "officialTitle": "",
    "officialType": "-1",
    "opusCount": "18",
    "playCount": "74.99w",
    "profession": null,
    "rankPosition": 74,
    "sex": "女",
    "type": "影视",
    "videoReviewCount": "2848"
  },
  {
    "coinCount": "5273",
    "face": "https://i0.hdslb.com/bfs/face/6aac72712a65aa6a525923602e1b2812c6472a45.jpg",
    "followerDiff": "4437",
    "isCollect": null,
    "level": "6",
    "likeCount": "3.24w",
    "maxSex": {
      "count": "476",
      "key": "女",
      "rate": "23.94%"
    },
    "mid": "1527375735",
    "name": "RICH徐大花",
    "newrankIndex": "822.3",
    "officialTitle": "",
    "officialType": "-1",
    "opusCount": "2",
    "playCount": "92.98w",
    "profession": null,
    "rankPosition": 75,
    "sex": "女",
    "type": "影视",
    "videoReviewCount": "3342"
  },
  {
    "coinCount": "919",
    "face": "https://i1.hdslb.com/bfs/face/6f28601a75bec02e85bbe33e3302f87d7cd9c2c9.jpg",
    "followerDiff": "7101",
    "isCollect": null,
    "level": "6",
    "likeCount": "4.09w",
    "maxSex": {
      "count": "0",
      "key": "男",
      "rate": "59.51%"
    },
    "mid": "96483112",
    "name": "0011LLYY",
    "newrankIndex": "821.3",
    "officialTitle": "bilibili 知名UP主",
    "officialType": "0",
    "opusCount": "2",
    "playCount": "178.66w",
    "profession": null,
    "rankPosition": 76,
    "sex": "保密",
    "type": "影视",
    "videoReviewCount": "355"
  },
  {
    "coinCount": "6214",
    "face": "https://i1.hdslb.com/bfs/face/829130e1b31e4a9de42687d27e7adf8a9448e46b.jpg",
    "followerDiff": "4848",
    "isCollect": null,
    "level": "6",
    "likeCount": "1.40w",
    "maxSex": {
      "count": "0",
      "key": "男",
      "rate": "89.46%"
    },
    "mid": "588554491",
    "name": "聊会电影吧",
    "newrankIndex": "818.5",
    "officialTitle": "bilibili 知名影视UP主",
    "officialType": "0",
    "opusCount": "2",
    "playCount": "25.09w",
    "profession": null,
    "rankPosition": 77,
    "sex": "男",
    "type": "影视",
    "videoReviewCount": "1098"
  },
  {
    "coinCount": "1.18w",
    "face": "https://i1.hdslb.com/bfs/face/659f96e349632bb64756d47b75b24b87421f2e95.jpg",
    "followerDiff": "827",
    "isCollect": null,
    "level": "6",
    "likeCount": "2.42w",
    "maxSex": {
      "count": "0",
      "key": "女",
      "rate": "90.83%"
    },
    "mid": "1540999",
    "name": "五彩哥哥",
    "newrankIndex": "818.4",
    "officialTitle": "bilibili 知名娱乐UP主",
    "officialType": "0",
    "opusCount": "6",
    "playCount": "31.02w",
    "profession": null,
    "rankPosition": 78,
    "sex": "女",
    "type": "影视",
    "videoReviewCount": "5032"
  },
  {
    "coinCount": "2495",
    "face": "https://i1.hdslb.com/bfs/face/d702cc51c846cc7f6a73bd67934929cc3508e5b5.jpg",
    "followerDiff": "2925",
    "isCollect": null,
    "level": "6",
    "likeCount": "1.06w",
    "maxSex": {
      "count": "0",
      "key": "男",
      "rate": "81.13%"
    },
    "mid": "17223352",
    "name": "1900影剧室",
    "newrankIndex": "816.1",
    "officialTitle": "bilibili 2021百大UP主、知名UP主",
    "officialType": "0",
    "opusCount": "1",
    "playCount": "18.60w",
    "profession": null,
    "rankPosition": 79,
    "sex": "男",
    "type": "影视",
    "videoReviewCount": "1163"
  },
  {
    "coinCount": "2319",
    "face": "http://i1.hdslb.com/bfs/face/55dbcb914506aeda2d7d57da51ef62a3e58a4928.jpg",
    "followerDiff": "1544",
    "isCollect": null,
    "level": "6",
    "likeCount": "2.30w",
    "maxSex": {
      "count": "0",
      "key": "男",
      "rate": "73.14%"
    },
    "mid": "386186788",
    "name": "据说放映",
    "newrankIndex": "814.7",
    "officialTitle": "",
    "officialType": "-1",
    "opusCount": "3",
    "playCount": "46.27w",
    "profession": null,
    "rankPosition": 80,
    "sex": "保密",
    "type": "影视",
    "videoReviewCount": "2338"
  },
  {
    "coinCount": "909",
    "face": "https://i0.hdslb.com/bfs/face/d5a0c67ea272b47ddb28b6ab46c1a99b11a0c6d7.jpg",
    "followerDiff": "1.12w",
    "isCollect": null,
    "level": "4",
    "likeCount": "26.63w",
    "maxSex": {
      "count": "53",
      "key": "男",
      "rate": "15.68%"
    },
    "mid": "3493123676179242",
    "name": "闲不住的克勤",
    "newrankIndex": "813.0",
    "officialTitle": "",
    "officialType": "-1",
    "opusCount": "5",
    "playCount": "315.45w",
    "profession": null,
    "rankPosition": 81,
    "sex": "保密",
    "type": "影视",
    "videoReviewCount": "660"
  },
  {
    "coinCount": "2876",
    "face": "https://i2.hdslb.com/bfs/face/f1385ce3cfabb81dee55be8ccfdab01d72edd03b.jpg",
    "followerDiff": "2001",
    "isCollect": null,
    "level": "6",
    "likeCount": "2.19w",
    "maxSex": {
      "count": "0",
      "key": "女",
      "rate": "62.98%"
    },
    "mid": "242020511",
    "name": "我是影Sir",
    "newrankIndex": "812.1",
    "officialTitle": "bilibili 知名影视UP主",
    "officialType": "0",
    "opusCount": "3",
    "playCount": "36.53w",
    "profession": null,
    "rankPosition": 82,
    "sex": "女",
    "type": "影视",
    "videoReviewCount": "1455"
  },
  {
    "coinCount": "2659",
    "face": "https://i2.hdslb.com/bfs/face/e9c5d94d2df887cf159cce6628609d0067b77f8f.jpg",
    "followerDiff": "4836",
    "isCollect": null,
    "level": "5",
    "likeCount": "2.79w",
    "maxSex": {
      "count": "414",
      "key": "男",
      "rate": "19.86%"
    },
    "mid": "625402577",
    "name": "探长日记",
    "newrankIndex": "810.9",
    "officialTitle": "",
    "officialType": "-1",
    "opusCount": "1",
    "playCount": "150.05w",
    "profession": null,
    "rankPosition": 83,
    "sex": "保密",
    "type": "影视",
    "videoReviewCount": "923"
  },
  {
    "coinCount": "882",
    "face": "http://i1.hdslb.com/bfs/face/6517e0c141ed226452f97a1ceb78d598068d7ef3.jpg",
    "followerDiff": "2171",
    "isCollect": null,
    "level": "6",
    "likeCount": "4.69w",
    "maxSex": {
      "count": "0",
      "key": "男",
      "rate": "86.12%"
    },
    "mid": "402155737",
    "name": "编剧雷神",
    "newrankIndex": "810.9",
    "officialTitle": "导演，《平行森林》导演、编剧",
    "officialType": "0",
    "opusCount": "6",
    "playCount": "93.38w",
    "profession": null,
    "rankPosition": 84,
    "sex": "保密",
    "type": "影视",
    "videoReviewCount": "1257"
  },
  {
    "coinCount": "1247",
    "face": "https://i0.hdslb.com/bfs/face/0be7e19057fc6adb55c576fd442632d3569c7d21.jpg",
    "followerDiff": "5761",
    "isCollect": null,
    "level": "6",
    "likeCount": "2.33w",
    "maxSex": {
      "count": "0",
      "key": "男",
      "rate": "88.59%"
    },
    "mid": "578425533",
    "name": "往往老布",
    "newrankIndex": "810.8",
    "officialTitle": "往往老布官方账号",
    "officialType": "0",
    "opusCount": "1",
    "playCount": "38.13w",
    "profession": null,
    "rankPosition": 85,
    "sex": "保密",
    "type": "影视",
    "videoReviewCount": "396"
  },
  {
    "coinCount": "4363",
    "face": "https://i2.hdslb.com/bfs/face/672591fefa66831f72edcc011454c595733d32fb.jpg",
    "followerDiff": "1654",
    "isCollect": null,
    "level": "6",
    "likeCount": "1.61w",
    "maxSex": {
      "count": "0",
      "key": "男",
      "rate": "96.16%"
    },
    "mid": "472013291",
    "name": "变相怪杰Mask",
    "newrankIndex": "810.3",
    "officialTitle": "bilibili 知名UP主",
    "officialType": "0",
    "opusCount": "1",
    "playCount": "25.34w",
    "profession": null,
    "rankPosition": 86,
    "sex": "保密",
    "type": "影视",
    "videoReviewCount": "1655"
  },
  {
    "coinCount": "2357",
    "face": "https://i1.hdslb.com/bfs/face/169bf4d98cccc9dbfe9ca5a39ff74c534a981c7d.jpg",
    "followerDiff": "701",
    "isCollect": null,
    "level": "6",
    "likeCount": "6.63w",
    "maxSex": {
      "count": "0",
      "key": "女",
      "rate": "50.75%"
    },
    "mid": "12855280",
    "name": "颜值爆表啦",
    "newrankIndex": "809.6",
    "officialTitle": "bilibili 知名影视UP主",
    "officialType": "0",
    "opusCount": "6",
    "playCount": "143.08w",
    "profession": null,
    "rankPosition": 87,
    "sex": "保密",
    "type": "影视",
    "videoReviewCount": "1307"
  },
  {
    "coinCount": "1451",
    "face": "https://i2.hdslb.com/bfs/face/cbf60ab887d0ebf963175cf642aa6b38132e36ea.jpg",
    "followerDiff": "1281",
    "isCollect": null,
    "level": "6",
    "likeCount": "1.44w",
    "maxSex": {
      "count": "0",
      "key": "男",
      "rate": "86.89%"
    },
    "mid": "700823648",
    "name": "大铁牛Game",
    "newrankIndex": "809.2",
    "officialTitle": "",
    "officialType": "-1",
    "opusCount": "2",
    "playCount": "132.01w",
    "profession": null,
    "rankPosition": 88,
    "sex": "男",
    "type": "影视",
    "videoReviewCount": "462"
  },
  {
    "coinCount": "2168",
    "face": "https://i1.hdslb.com/bfs/face/4204312bf686f61d25fad5d293f7ebd105e1d7a8.jpg",
    "followerDiff": "2087",
    "isCollect": null,
    "level": "6",
    "likeCount": "1.72w",
    "maxSex": {
      "count": "0",
      "key": "男",
      "rate": "71.62%"
    },
    "mid": "188807182",
    "name": "吾聊电影",
    "newrankIndex": "808.5",
    "officialTitle": "bilibili 知名影视UP主",
    "officialType": "0",
    "opusCount": "1",
    "playCount": "93.20w",
    "profession": null,
    "rankPosition": 89,
    "sex": "男",
    "type": "影视",
    "videoReviewCount": "1063"
  },
  {
    "coinCount": "4230",
    "face": "https://i1.hdslb.com/bfs/face/410ccc94768d178926e0c7986251047bf14ed79e.jpg",
    "followerDiff": "4442",
    "isCollect": null,
    "level": "6",
    "likeCount": "5928",
    "maxSex": {
      "count": "0",
      "key": "男",
      "rate": "76.11%"
    },
    "mid": "669154966",
    "name": "椒盐说影",
    "newrankIndex": "808.4",
    "officialTitle": "bilibili 知名影视UP主",
    "officialType": "0",
    "opusCount": "1",
    "playCount": "9.47w",
    "profession": null,
    "rankPosition": 90,
    "sex": "男",
    "type": "影视",
    "videoReviewCount": "747"
  },
  {
    "coinCount": "8237",
    "face": "https://i2.hdslb.com/bfs/face/dec94ea70a7af4bd82f249282b9e7abec28608ed.jpg",
    "followerDiff": "2829",
    "isCollect": null,
    "level": "6",
    "likeCount": "9404",
    "maxSex": {
      "count": "0",
      "key": "男",
      "rate": "83.55%"
    },
    "mid": "559186307",
    "name": "前进四放映室",
    "newrankIndex": "807.9",
    "officialTitle": "bilibili 知名影视UP主",
    "officialType": "0",
    "opusCount": "1",
    "playCount": "4.20w",
    "profession": null,
    "rankPosition": 91,
    "sex": "保密",
    "type": "影视",
    "videoReviewCount": "411"
  },
  {
    "coinCount": "6573",
    "face": "https://i0.hdslb.com/bfs/face/3815118449e75cafc40ebfc19f91a06c44a48a36.jpg",
    "followerDiff": "1179",
    "isCollect": null,
    "level": "6",
    "likeCount": "8.65w",
    "maxSex": {
      "count": "1549",
      "key": "女",
      "rate": "21.75%"
    },
    "mid": "5112039",
    "name": "朕好饿啊",
    "newrankIndex": "804.5",
    "officialTitle": "",
    "officialType": "-1",
    "opusCount": "4",
    "playCount": "93.14w",
    "profession": null,
    "rankPosition": 92,
    "sex": "保密",
    "type": "影视",
    "videoReviewCount": "425"
  },
  {
    "coinCount": "8018",
    "face": "https://i1.hdslb.com/bfs/face/d9a321858de83ebc8ef5b4978ca0222a3673d9e4.jpg",
    "followerDiff": "1208",
    "isCollect": null,
    "level": "6",
    "likeCount": "2.50w",
    "maxSex": {
      "count": "0",
      "key": "女",
      "rate": "93.85%"
    },
    "mid": "1100835241",
    "name": "太好磕了鸭",
    "newrankIndex": "803.8",
    "officialTitle": "",
    "officialType": "-1",
    "opusCount": "2",
    "playCount": "21.88w",
    "profession": null,
    "rankPosition": 93,
    "sex": "女",
    "type": "影视",
    "videoReviewCount": "1424"
  },
  {
    "coinCount": "1.15w",
    "face": "https://i1.hdslb.com/bfs/face/9a5a5974e87d42da0e0a684a13f1de04f6ac48f5.jpg",
    "followerDiff": "1142",
    "isCollect": null,
    "level": "6",
    "likeCount": "1.52w",
    "maxSex": {
      "count": "0",
      "key": "男",
      "rate": "88.65%"
    },
    "mid": "16848214",
    "name": "帝国星哥",
    "newrankIndex": "803.7",
    "officialTitle": "bilibili 知名UP主",
    "officialType": "0",
    "opusCount": "2",
    "playCount": "13.68w",
    "profession": null,
    "rankPosition": 94,
    "sex": "男",
    "type": "影视",
    "videoReviewCount": "1231"
  },
  {
    "coinCount": "3203",
    "face": "https://i1.hdslb.com/bfs/face/7b723736088cc30040d30bc6d41b89e40b53b221.jpg",
    "followerDiff": "1391",
    "isCollect": null,
    "level": "5",
    "likeCount": "3.01w",
    "maxSex": {
      "count": "457",
      "key": "男",
      "rate": "15.27%"
    },
    "mid": "1716152596",
    "name": "失恋影视",
    "newrankIndex": "802.7",
    "officialTitle": "",
    "officialType": "-1",
    "opusCount": "4",
    "playCount": "125.12w",
    "profession": null,
    "rankPosition": 95,
    "sex": "男",
    "type": "影视",
    "videoReviewCount": "2863"
  },
  {
    "coinCount": "4674",
    "face": "https://i1.hdslb.com/bfs/face/c7ed29000a683df676a542ee159a00fa483d574c.jpg",
    "followerDiff": "4823",
    "isCollect": null,
    "level": "6",
    "likeCount": "5.75w",
    "maxSex": {
      "count": "96",
      "key": "女",
      "rate": "23.76%"
    },
    "mid": "382342243",
    "name": "小号小号别问了是小号",
    "newrankIndex": "801.8",
    "officialTitle": "",
    "officialType": "-1",
    "opusCount": "1",
    "playCount": "48.82w",
    "profession": null,
    "rankPosition": 96,
    "sex": "保密",
    "type": "影视",
    "videoReviewCount": "2665"
  },
  {
    "coinCount": "4357",
    "face": "https://i0.hdslb.com/bfs/face/ec007951c1fc7dfd248436b8975e4d284334ce6b.jpg",
    "followerDiff": "2832",
    "isCollect": null,
    "level": "6",
    "likeCount": "2.36w",
    "maxSex": {
      "count": "915",
      "key": "男",
      "rate": "19.34%"
    },
    "mid": "517507881",
    "name": "观察者Q先生",
    "newrankIndex": "801.7",
    "officialTitle": "",
    "officialType": "-1",
    "opusCount": "4",
    "playCount": "29.52w",
    "profession": null,
    "rankPosition": 97,
    "sex": "男",
    "type": "影视",
    "videoReviewCount": "949"
  },
  {
    "coinCount": "1767",
    "face": "https://i0.hdslb.com/bfs/face/452f239756a610ef39b377b32b2b140f9794b487.jpg",
    "followerDiff": "4777",
    "isCollect": null,
    "level": "6",
    "likeCount": "11.11w",
    "maxSex": {
      "count": "0",
      "key": "女",
      "rate": "52.53%"
    },
    "mid": "1614789471",
    "name": "派小轩",
    "newrankIndex": "801.3",
    "officialTitle": "派小轩官方账号，短剧UP主",
    "officialType": "0",
    "opusCount": "1",
    "playCount": "142.76w",
    "profession": null,
    "rankPosition": 98,
    "sex": "保密",
    "type": "影视",
    "videoReviewCount": "327"
  },
  {
    "coinCount": "1434",
    "face": "https://i2.hdslb.com/bfs/face/3c9d436659037cc17fe0d32975ef7f17710ba820.jpg",
    "followerDiff": "1311",
    "isCollect": null,
    "level": "6",
    "likeCount": "2.10w",
    "maxSex": {
      "count": "0",
      "key": "男",
      "rate": "83.83%"
    },
    "mid": "58852835",
    "name": "牛叔万岁万岁万万岁",
    "newrankIndex": "799.5",
    "officialTitle": "bilibili 知名影视UP主",
    "officialType": "0",
    "opusCount": "2",
    "playCount": "60.92w",
    "profession": null,
    "rankPosition": 99,
    "sex": "男",
    "type": "影视",
    "videoReviewCount": "999"
  },
  {
    "coinCount": "2043",
    "face": "https://i1.hdslb.com/bfs/face/c63d9aff4093d745e57dfcc8bc2713667f0605d7.jpg",
    "followerDiff": "1358",
    "isCollect": null,
    "level": "6",
    "likeCount": "6.77w",
    "maxSex": {
      "count": "940",
      "key": "男",
      "rate": "28.46%"
    },
    "mid": "1357372759",
    "name": "碱性蛋白",
    "newrankIndex": "797.9",
    "officialTitle": "bilibili 知名短剧UP主",
    "officialType": "0",
    "opusCount": "2",
    "playCount": "123.97w",
    "profession": null,
    "rankPosition": 100,
    "sex": "男",
    "type": "影视",
    "videoReviewCount": "687"
  }
]
